Workbook

Sheet Start Quote
B2: RENTAL QUOTE — START QUOTE
B3: Gas detection equipment rental. Enter quote & customer details. Yellow cells are inputs.
B5: LEGEND: | C5: Input | E5: Calculated
B7: QUOTE DETAILS
B8: Quote Number | E8: Rental Start Date
B9: Quote Date | E9: Rental End Date
B10: Valid Through | C10: =IF(AND(ISNUMBER(C9),ISNUMBER(F11)),C9+F11,"") | E10: Default Rental Days | F10: =IF(AND(ISNUMBER(F8),ISNUMBER(F9)),MAX(1,F9-F8+1),"")
B11: Salesperson | E11: Validity (days) | F11: 30
B13: CUSTOMER INFORMATION
B14: Customer / Company | E14: Phone
B15: Contact Name | E15: Project / Site
B16: Email
B18: CHARGES & TAX
B19: Tax Rate | C19: 0 | E19: Configured Equipment | F19: =Config_Subtotal -> 0
B20: Freight | C20: 0 | E20: Accessories & Services | F20: =Acc_Subtotal -> 0
B21: Miscellaneous Charge | C21: 0 | E21: Subtotal | F21: =Config_Subtotal+Acc_Subtotal -> 0
E22: Grand Total | F22: =F21+ROUND(F21*Tax_Rate,2)+Freight+Misc_Charge -> 0
B24: NOTES
B25: Customer Notes
B27: Internal Notes

Sheet Guided Configurator
B2: GUIDED CONFIGURATOR
B3: Configure up to 10 multi-gas units. Pick Device, then individually select LEL, O2, Toxic 1 and Toxic 2 sensors. Daily rate = base rental (USD List col C) + sensor upgrade surcharges. Yellow = input; grey = calculated.
B5: Legend: | C5: Input | D5: Calculated
B7: # | C7: Device | D7: LEL Sensor | E7: O2 | F7: Toxic 1 | G7: Toxic 2 | H7: Qty | I7: Days | J7: Disc % | K7: Base Daily | L7: Sensor Upg. Daily | M7: Unit Daily | N7: Extended Total | O7: Config Code | P7: Configuration Description | Q7: Status | R7: EXO 8-Gas Expansion Module | S7: Module Daily
B8: 1 | D8: LEL-IR | E8: O2 | F8: No Sensor | G8: No Sensor | H8: 1 | I8: =IF(ISNUMBER(Default_Days),Default_Days,1) -> 1 | J8: 0 | K8: =IF($C8="","",IFERROR(INDEX(DB_Rate,MATCH(IFERROR(INDEX(DeviceMap,MATCH($C8,INDEX(DeviceMap,0,1),0),2),""),DB_Key,0)),"?")) | L8: =IF($C8="","",IF(OR($D8="",$D8="No Sensor"),0,IF(IFERROR(INDEX(SensorTier,MATCH($D8,SensorName,0)),"Standard")="Standard",0,IFERROR(INDEX(DB_Rate,MATCH(IFERROR(INDEX(TierKeys,MATCH(IFERROR(INDEX(SensorTier,MATCH($D8,SensorName,0)),"Standard"),INDEX(TierKeys,0,1),0),2),""),DB_Key,0)),0)))+IF(OR($E8="",$E8="No Sensor"),0,IF(IFERROR(INDEX(SensorTier,MATCH($E8,SensorName,0)),"Standard")="Standard",0,IFERROR(INDEX(DB_Rate,MATCH(IFERROR(INDEX(TierKeys,MATCH(IFERROR(INDEX(SensorTier,MATCH($E8,SensorName,0)),"Standard"),INDEX(TierKeys,0,1),0),2),""),DB_Key,0)),0)))+IF(OR($F8="",$F8="No Sensor"),0,IF(IFERROR(INDEX(SensorTier,MATCH($F8,SensorName,0)),"Standard")="Standard",0,IFERROR(INDEX(DB_Rate,MATCH(IFERROR(INDEX(TierKeys,MATCH(IFERROR(INDEX(SensorTier,MATCH($F8,SensorName,0)),"Standard"),INDEX(TierKeys,0,1),0),2),""),DB_Key,0)),0)))+IF(OR($G8="",$G8="No Sensor"),0,IF(IFERROR(INDEX(SensorTier,MATCH($G8,SensorName,0)),"Standard")="Standard",0,IFERROR(INDEX(DB_Rate,MATCH(IFERROR(INDEX(TierKeys,MATCH(IFERROR(INDEX(SensorTier,MATCH($G8,SensorName,0)),"Standard"),INDEX(TierKeys,0,1),0),2),""),DB_Key,0)),0)))) | M8: =IF($C8="","",IF(ISNUMBER($K8),$K8+$L8+$S8,"")) | N8: =IF(AND($C8<>"",ISNUMBER($M8)),$H8*$I8*$M8*(1-$J8),0) -> 0 | O8: =IF($C8="","",SUBSTITUTE(IFERROR(INDEX(DeviceMap,MATCH($C8,INDEX(DeviceMap,0,1),0),3),""),"~",IF(OR($R8="",$R8="No Module"),"X",IFERROR(INDEX(GEMMap,MATCH($R8,INDEX(GEMMap,0,1),0),2),"X")))&"-"&$X8&"-1D") | P8: =IF($C8="","",$C8&", with ("&TEXTJOIN("/",TRUE,IF($D8="No Sensor","",$D8),IF($E8="No Sensor","",$E8),IF($F8="No Sensor","",$F8),IF($G8="No Sensor","",$G8))&")"&IF(OR($R8="",$R8="No Module"),""," + 8-gas expansion module: "&$R8)) | Q8: =IF($C8="","",IF(AND($R8<>"",$R8<>"No Module",ISERROR(SEARCH("EXO",$C8))),"Module needs EXO device",IF(OR($K8="?",NOT(ISNUMBER($M8))),"Unknown rate",IF(AND($F8<>"No Sensor",$F8=$G8),"Duplicate sensors",IF(AND($D8="No Sensor",$E8="No Sensor",$F8="No Sensor",$G8="No Sensor"),"Review: no sensors","Complete"))))) | R8: No Module | S8: =IF($C8="","",IF(OR($R8="",$R8="No Module"),0,IFERROR(INDEX(DB_Rate,MATCH(INDEX(GEMMap,MATCH($R8,INDEX(GEMMap,0,1),0),3),DB_Key,0)),0))) | T8: =CODE(IFERROR(INDEX(SensorCode,MATCH($D8,SensorName,0)),"X")) | U8: =CODE(IFERROR(INDEX(SensorCode,MATCH($E8,SensorName,0)),"X")) | V8: =CODE(IFERROR(INDEX(SensorCode,MATCH($F8,SensorName,0)),"X")) | W8: =CODE(IFERROR(INDEX(SensorCode,MATCH($G8,SensorName,0)),"X")) | X8: =CHAR(SMALL($T8:$W8,1))&CHAR(SMALL($T8:$W8,2))&CHAR(SMALL($T8:$W8,3))&CHAR(SMALL($T8:$W8,4))
B9: 2 | D9: LEL-IR | E9: O2 | F9: No Sensor | G9: No Sensor | H9: 1 | I9: =IF(ISNUMBER(Default_Days),Default_Days,1) -> 1 | J9: 0 | K9: =IF($C9="","",IFERROR(INDEX(DB_Rate,MATCH(IFERROR(INDEX(DeviceMap,MATCH($C9,INDEX(DeviceMap,0,1),0),2),""),DB_Key,0)),"?")) | L9: =IF($C9="","",IF(OR($D9="",$D9="No Sensor"),0,IF(IFERROR(INDEX(SensorTier,MATCH($D9,SensorName,0)),"Standard")="Standard",0,IFERROR(INDEX(DB_Rate,MATCH(IFERROR(INDEX(TierKeys,MATCH(IFERROR(INDEX(SensorTier,MATCH($D9,SensorName,0)),"Standard"),INDEX(TierKeys,0,1),0),2),""),DB_Key,0)),0)))+IF(OR($E9="",$E9="No Sensor"),0,IF(IFERROR(INDEX(SensorTier,MATCH($E9,SensorName,0)),"Standard")="Standard",0,IFERROR(INDEX(DB_Rate,MATCH(IFERROR(INDEX(TierKeys,MATCH(IFERROR(INDEX(SensorTier,MATCH($E9,SensorName,0)),"Standard"),INDEX(TierKeys,0,1),0),2),""),DB_Key,0)),0)))+IF(OR($F9="",$F9="No Sensor"),0,IF(IFERROR(INDEX(SensorTier,MATCH($F9,SensorName,0)),"Standard")="Standard",0,IFERROR(INDEX(DB_Rate,MATCH(IFERROR(INDEX(TierKeys,MATCH(IFERROR(INDEX(SensorTier,MATCH($F9,SensorName,0)),"Standard"),INDEX(TierKeys,0,1),0),2),""),DB_Key,0)),0)))+IF(OR($G9="",$G9="No Sensor"),0,IF(IFERROR(INDEX(SensorTier,MATCH($G9,SensorName,0)),"Standard")="Standard",0,IFERROR(INDEX(DB_Rate,MATCH(IFERROR(INDEX(TierKeys,MATCH(IFERROR(INDEX(SensorTier,MATCH($G9,SensorName,0)),"Standard"),INDEX(TierKeys,0,1),0),2),""),DB_Key,0)),0)))) | M9: =IF($C9="","",IF(ISNUMBER($K9),$K9+$L9+$S9,"")) | N9: =IF(AND($C9<>"",ISNUMBER($M9)),$H9*$I9*$M9*(1-$J9),0) -> 0 | O9: =IF($C9="","",SUBSTITUTE(IFERROR(INDEX(DeviceMap,MATCH($C9,INDEX(DeviceMap,0,1),0),3),""),"~",IF(OR($R9="",$R9="No Module"),"X",IFERROR(INDEX(GEMMap,MATCH($R9,INDEX(GEMMap,0,1),0),2),"X")))&"-"&$X9&"-1D") | P9: =IF($C9="","",$C9&", with ("&TEXTJOIN("/",TRUE,IF($D9="No Sensor","",$D9),IF($E9="No Sensor","",$E9),IF($F9="No Sensor","",$F9),IF($G9="No Sensor","",$G9))&")"&IF(OR($R9="",$R9="No Module"),""," + 8-gas expansion module: "&$R9)) | Q9: =IF($C9="","",IF(AND($R9<>"",$R9<>"No Module",ISERROR(SEARCH("EXO",$C9))),"Module needs EXO device",IF(OR($K9="?",NOT(ISNUMBER($M9))),"Unknown rate",IF(AND($F9<>"No Sensor",$F9=$G9),"Duplicate sensors",IF(AND($D9="No Sensor",$E9="No Sensor",$F9="No Sensor",$G9="No Sensor"),"Review: no sensors","Complete"))))) | R9: No Module | S9: =IF($C9="","",IF(OR($R9="",$R9="No Module"),0,IFERROR(INDEX(DB_Rate,MATCH(INDEX(GEMMap,MATCH($R9,INDEX(GEMMap,0,1),0),3),DB_Key,0)),0))) | T9: =CODE(IFERROR(INDEX(SensorCode,MATCH($D9,SensorName,0)),"X")) | U9: =CODE(IFERROR(INDEX(SensorCode,MATCH($E9,SensorName,0)),"X")) | V9: =CODE(IFERROR(INDEX(SensorCode,MATCH($F9,SensorName,0)),"X")) | W9: =CODE(IFERROR(INDEX(SensorCode,MATCH($G9,SensorName,0)),"X")) | X9: =CHAR(SMALL($T9:$W9,1))&CHAR(SMALL($T9:$W9,2))&CHAR(SMALL($T9:$W9,3))&CHAR(SMALL($T9:$W9,4))
B10: 3 | D10: LEL-IR | E10: O2 | F10: No Sensor | G10: No Sensor | H10: 1 | I10: =IF(ISNUMBER(Default_Days),Default_Days,1) -> 1 | J10: 0 | K10: =IF($C10="","",IFERROR(INDEX(DB_Rate,MATCH(IFERROR(INDEX(DeviceMap,MATCH($C10,INDEX(DeviceMap,0,1),0),2),""),DB_Key,0)),"?")) | L10: =IF($C10="","",IF(OR($D10="",$D10="No Sensor"),0,IF(IFERROR(INDEX(SensorTier,MATCH($D10,SensorName,0)),"Standard")="Standard",0,IFERROR(INDEX(DB_Rate,MATCH(IFERROR(INDEX(TierKeys,MATCH(IFERROR(INDEX(SensorTier,MATCH($D10,SensorName,0)),"Standard"),INDEX(TierKeys,0,1),0),2),""),DB_Key,0)),0)))+IF(OR($E10="",$E10="No Sensor"),0,IF(IFERROR(INDEX(SensorTier,MATCH($E10,SensorName,0)),"Standard")="Standard",0,IFERROR(INDEX(DB_Rate,MATCH(IFERROR(INDEX(TierKeys,MATCH(IFERROR(INDEX(SensorTier,MATCH($E10,SensorName,0)),"Standard"),INDEX(TierKeys,0,1),0),2),""),DB_Key,0)),0)))+IF(OR($F10="",$F10="No Sensor"),0,IF(IFERROR(INDEX(SensorTier,MATCH($F10,SensorName,0)),"Standard")="Standard",0,IFERROR(INDEX(DB_Rate,MATCH(IFERROR(INDEX(TierKeys,MATCH(IFERROR(INDEX(SensorTier,MATCH($F10,SensorName,0)),"Standard"),INDEX(TierKeys,0,1),0),2),""),DB_Key,0)),0)))+IF(OR($G10="",$G10="No Sensor"),0,IF(IFERROR(INDEX(SensorTier,MATCH($G10,SensorName,0)),"Standard")="Standard",0,IFERROR(INDEX(DB_Rate,MATCH(IFERROR(INDEX(TierKeys,MATCH(IFERROR(INDEX(SensorTier,MATCH($G10,SensorName,0)),"Standard"),INDEX(TierKeys,0,1),0),2),""),DB_Key,0)),0)))) | M10: =IF($C10="","",IF(ISNUMBER($K10),$K10+$L10+$S10,"")) | N10: =IF(AND($C10<>"",ISNUMBER($M10)),$H10*$I10*$M10*(1-$J10),0) -> 0 | O10: =IF($C10="","",SUBSTITUTE(IFERROR(INDEX(DeviceMap,MATCH($C10,INDEX(DeviceMap,0,1),0),3),""),"~",IF(OR($R10="",$R10="No Module"),"X",IFERROR(INDEX(GEMMap,MATCH($R10,INDEX(GEMMap,0,1),0),2),"X")))&"-"&$X10&"-1D") | P10: =IF($C10="","",$C10&", with ("&TEXTJOIN("/",TRUE,IF($D10="No Sensor","",$D10),IF($E10="No Sensor","",$E10),IF($F10="No Sensor","",$F10),IF($G10="No Sensor","",$G10))&")"&IF(OR($R10="",$R10="No Module"),""," + 8-gas expansion module: "&$R10)) | Q10: =IF($C10="","",IF(AND($R10<>"",$R10<>"No Module",ISERROR(SEARCH("EXO",$C10))),"Module needs EXO device",IF(OR($K10="?",NOT(ISNUMBER($M10))),"Unknown rate",IF(AND($F10<>"No Sensor",$F10=$G10),"Duplicate sensors",IF(AND($D10="No Sensor",$E10="No Sensor",$F10="No Sensor",$G10="No Sensor"),"Review: no sensors","Complete"))))) | R10: No Module | S10: =IF($C10="","",IF(OR($R10="",$R10="No Module"),0,IFERROR(INDEX(DB_Rate,MATCH(INDEX(GEMMap,MATCH($R10,INDEX(GEMMap,0,1),0),3),DB_Key,0)),0))) | T10: =CODE(IFERROR(INDEX(SensorCode,MATCH($D10,SensorName,0)),"X")) | U10: =CODE(IFERROR(INDEX(SensorCode,MATCH($E10,SensorName,0)),"X")) | V10: =CODE(IFERROR(INDEX(SensorCode,MATCH($F10,SensorName,0)),"X")) | W10: =CODE(IFERROR(INDEX(SensorCode,MATCH($G10,SensorName,0)),"X")) | X10: =CHAR(SMALL($T10:$W10,1))&CHAR(SMALL($T10:$W10,2))&CHAR(SMALL($T10:$W10,3))&CHAR(SMALL($T10:$W10,4))
B11: 4 | D11: LEL-IR | E11: O2 | F11: No Sensor | G11: No Sensor | H11: 1 | I11: =IF(ISNUMBER(Default_Days),Default_Days,1) -> 1 | J11: 0 | K11: =IF($C11="","",IFERROR(INDEX(DB_Rate,MATCH(IFERROR(INDEX(DeviceMap,MATCH($C11,INDEX(DeviceMap,0,1),0),2),""),DB_Key,0)),"?")) | L11: =IF($C11="","",IF(OR($D11="",$D11="No Sensor"),0,IF(IFERROR(INDEX(SensorTier,MATCH($D11,SensorName,0)),"Standard")="Standard",0,IFERROR(INDEX(DB_Rate,MATCH(IFERROR(INDEX(TierKeys,MATCH(IFERROR(INDEX(SensorTier,MATCH($D11,SensorName,0)),"Standard"),INDEX(TierKeys,0,1),0),2),""),DB_Key,0)),0)))+IF(OR($E11="",$E11="No Sensor"),0,IF(IFERROR(INDEX(SensorTier,MATCH($E11,SensorName,0)),"Standard")="Standard",0,IFERROR(INDEX(DB_Rate,MATCH(IFERROR(INDEX(TierKeys,MATCH(IFERROR(INDEX(SensorTier,MATCH($E11,SensorName,0)),"Standard"),INDEX(TierKeys,0,1),0),2),""),DB_Key,0)),0)))+IF(OR($F11="",$F11="No Sensor"),0,IF(IFERROR(INDEX(SensorTier,MATCH($F11,SensorName,0)),"Standard")="Standard",0,IFERROR(INDEX(DB_Rate,MATCH(IFERROR(INDEX(TierKeys,MATCH(IFERROR(INDEX(SensorTier,MATCH($F11,SensorName,0)),"Standard"),INDEX(TierKeys,0,1),0),2),""),DB_Key,0)),0)))+IF(OR($G11="",$G11="No Sensor"),0,IF(IFERROR(INDEX(SensorTier,MATCH($G11,SensorName,0)),"Standard")="Standard",0,IFERROR(INDEX(DB_Rate,MATCH(IFERROR(INDEX(TierKeys,MATCH(IFERROR(INDEX(SensorTier,MATCH($G11,SensorName,0)),"Standard"),INDEX(TierKeys,0,1),0),2),""),DB_Key,0)),0)))) | M11: =IF($C11="","",IF(ISNUMBER($K11),$K11+$L11+$S11,"")) | N11: =IF(AND($C11<>"",ISNUMBER($M11)),$H11*$I11*$M11*(1-$J11),0) -> 0 | O11: =IF($C11="","",SUBSTITUTE(IFERROR(INDEX(DeviceMap,MATCH($C11,INDEX(DeviceMap,0,1),0),3),""),"~",IF(OR($R11="",$R11="No Module"),"X",IFERROR(INDEX(GEMMap,MATCH($R11,INDEX(GEMMap,0,1),0),2),"X")))&"-"&$X11&"-1D") | P11: =IF($C11="","",$C11&", with ("&TEXTJOIN("/",TRUE,IF($D11="No Sensor","",$D11),IF($E11="No Sensor","",$E11),IF($F11="No Sensor","",$F11),IF($G11="No Sensor","",$G11))&")"&IF(OR($R11="",$R11="No Module"),""," + 8-gas expansion module: "&$R11)) | Q11: =IF($C11="","",IF(AND($R11<>"",$R11<>"No Module",ISERROR(SEARCH("EXO",$C11))),"Module needs EXO device",IF(OR($K11="?",NOT(ISNUMBER($M11))),"Unknown rate",IF(AND($F11<>"No Sensor",$F11=$G11),"Duplicate sensors",IF(AND($D11="No Sensor",$E11="No Sensor",$F11="No Sensor",$G11="No Sensor"),"Review: no sensors","Complete"))))) | R11: No Module | S11: =IF($C11="","",IF(OR($R11="",$R11="No Module"),0,IFERROR(INDEX(DB_Rate,MATCH(INDEX(GEMMap,MATCH($R11,INDEX(GEMMap,0,1),0),3),DB_Key,0)),0))) | T11: =CODE(IFERROR(INDEX(SensorCode,MATCH($D11,SensorName,0)),"X")) | U11: =CODE(IFERROR(INDEX(SensorCode,MATCH($E11,SensorName,0)),"X")) | V11: =CODE(IFERROR(INDEX(SensorCode,MATCH($F11,SensorName,0)),"X")) | W11: =CODE(IFERROR(INDEX(SensorCode,MATCH($G11,SensorName,0)),"X")) | X11: =CHAR(SMALL($T11:$W11,1))&CHAR(SMALL($T11:$W11,2))&CHAR(SMALL($T11:$W11,3))&CHAR(SMALL($T11:$W11,4))
B12: 5 | D12: LEL-IR | E12: O2 | F12: No Sensor | G12: No Sensor | H12: 1 | I12: =IF(ISNUMBER(Default_Days),Default_Days,1) -> 1 | J12: 0 | K12: =IF($C12="","",IFERROR(INDEX(DB_Rate,MATCH(IFERROR(INDEX(DeviceMap,MATCH($C12,INDEX(DeviceMap,0,1),0),2),""),DB_Key,0)),"?")) | L12: =IF($C12="","",IF(OR($D12="",$D12="No Sensor"),0,IF(IFERROR(INDEX(SensorTier,MATCH($D12,SensorName,0)),"Standard")="Standard",0,IFERROR(INDEX(DB_Rate,MATCH(IFERROR(INDEX(TierKeys,MATCH(IFERROR(INDEX(SensorTier,MATCH($D12,SensorName,0)),"Standard"),INDEX(TierKeys,0,1),0),2),""),DB_Key,0)),0)))+IF(OR($E12="",$E12="No Sensor"),0,IF(IFERROR(INDEX(SensorTier,MATCH($E12,SensorName,0)),"Standard")="Standard",0,IFERROR(INDEX(DB_Rate,MATCH(IFERROR(INDEX(TierKeys,MATCH(IFERROR(INDEX(SensorTier,MATCH($E12,SensorName,0)),"Standard"),INDEX(TierKeys,0,1),0),2),""),DB_Key,0)),0)))+IF(OR($F12="",$F12="No Sensor"),0,IF(IFERROR(INDEX(SensorTier,MATCH($F12,SensorName,0)),"Standard")="Standard",0,IFERROR(INDEX(DB_Rate,MATCH(IFERROR(INDEX(TierKeys,MATCH(IFERROR(INDEX(SensorTier,MATCH($F12,SensorName,0)),"Standard"),INDEX(TierKeys,0,1),0),2),""),DB_Key,0)),0)))+IF(OR($G12="",$G12="No Sensor"),0,IF(IFERROR(INDEX(SensorTier,MATCH($G12,SensorName,0)),"Standard")="Standard",0,IFERROR(INDEX(DB_Rate,MATCH(IFERROR(INDEX(TierKeys,MATCH(IFERROR(INDEX(SensorTier,MATCH($G12,SensorName,0)),"Standard"),INDEX(TierKeys,0,1),0),2),""),DB_Key,0)),0)))) | M12: =IF($C12="","",IF(ISNUMBER($K12),$K12+$L12+$S12,"")) | N12: =IF(AND($C12<>"",ISNUMBER($M12)),$H12*$I12*$M12*(1-$J12),0) -> 0 | O12: =IF($C12="","",SUBSTITUTE(IFERROR(INDEX(DeviceMap,MATCH($C12,INDEX(DeviceMap,0,1),0),3),""),"~",IF(OR($R12="",$R12="No Module"),"X",IFERROR(INDEX(GEMMap,MATCH($R12,INDEX(GEMMap,0,1),0),2),"X")))&"-"&$X12&"-1D") | P12: =IF($C12="","",$C12&", with ("&TEXTJOIN("/",TRUE,IF($D12="No Sensor","",$D12),IF($E12="No Sensor","",$E12),IF($F12="No Sensor","",$F12),IF($G12="No Sensor","",$G12))&")"&IF(OR($R12="",$R12="No Module"),""," + 8-gas expansion module: "&$R12)) | Q12: =IF($C12="","",IF(AND($R12<>"",$R12<>"No Module",ISERROR(SEARCH("EXO",$C12))),"Module needs EXO device",IF(OR($K12="?",NOT(ISNUMBER($M12))),"Unknown rate",IF(AND($F12<>"No Sensor",$F12=$G12),"Duplicate sensors",IF(AND($D12="No Sensor",$E12="No Sensor",$F12="No Sensor",$G12="No Sensor"),"Review: no sensors","Complete"))))) | R12: No Module | S12: =IF($C12="","",IF(OR($R12="",$R12="No Module"),0,IFERROR(INDEX(DB_Rate,MATCH(INDEX(GEMMap,MATCH($R12,INDEX(GEMMap,0,1),0),3),DB_Key,0)),0))) | T12: =CODE(IFERROR(INDEX(SensorCode,MATCH($D12,SensorName,0)),"X")) | U12: =CODE(IFERROR(INDEX(SensorCode,MATCH($E12,SensorName,0)),"X")) | V12: =CODE(IFERROR(INDEX(SensorCode,MATCH($F12,SensorName,0)),"X")) | W12: =CODE(IFERROR(INDEX(SensorCode,MATCH($G12,SensorName,0)),"X")) | X12: =CHAR(SMALL($T12:$W12,1))&CHAR(SMALL($T12:$W12,2))&CHAR(SMALL($T12:$W12,3))&CHAR(SMALL($T12:$W12,4))
B13: 6 | D13: LEL-IR | E13: O2 | F13: No Sensor | G13: No Sensor | H13: 1 | I13: =IF(ISNUMBER(Default_Days),Default_Days,1) -> 1 | J13: 0 | K13: =IF($C13="","",IFERROR(INDEX(DB_Rate,MATCH(IFERROR(INDEX(DeviceMap,MATCH($C13,INDEX(DeviceMap,0,1),0),2),""),DB_Key,0)),"?")) | L13: =IF($C13="","",IF(OR($D13="",$D13="No Sensor"),0,IF(IFERROR(INDEX(SensorTier,MATCH($D13,SensorName,0)),"Standard")="Standard",0,IFERROR(INDEX(DB_Rate,MATCH(IFERROR(INDEX(TierKeys,MATCH(IFERROR(INDEX(SensorTier,MATCH($D13,SensorName,0)),"Standard"),INDEX(TierKeys,0,1),0),2),""),DB_Key,0)),0)))+IF(OR($E13="",$E13="No Sensor"),0,IF(IFERROR(INDEX(SensorTier,MATCH($E13,SensorName,0)),"Standard")="Standard",0,IFERROR(INDEX(DB_Rate,MATCH(IFERROR(INDEX(TierKeys,MATCH(IFERROR(INDEX(SensorTier,MATCH($E13,SensorName,0)),"Standard"),INDEX(TierKeys,0,1),0),2),""),DB_Key,0)),0)))+IF(OR($F13="",$F13="No Sensor"),0,IF(IFERROR(INDEX(SensorTier,MATCH($F13,SensorName,0)),"Standard")="Standard",0,IFERROR(INDEX(DB_Rate,MATCH(IFERROR(INDEX(TierKeys,MATCH(IFERROR(INDEX(SensorTier,MATCH($F13,SensorName,0)),"Standard"),INDEX(TierKeys,0,1),0),2),""),DB_Key,0)),0)))+IF(OR($G13="",$G13="No Sensor"),0,IF(IFERROR(INDEX(SensorTier,MATCH($G13,SensorName,0)),"Standard")="Standard",0,IFERROR(INDEX(DB_Rate,MATCH(IFERROR(INDEX(TierKeys,MATCH(IFERROR(INDEX(SensorTier,MATCH($G13,SensorName,0)),"Standard"),INDEX(TierKeys,0,1),0),2),""),DB_Key,0)),0)))) | M13: =IF($C13="","",IF(ISNUMBER($K13),$K13+$L13+$S13,"")) | N13: =IF(AND($C13<>"",ISNUMBER($M13)),$H13*$I13*$M13*(1-$J13),0) -> 0 | O13: =IF($C13="","",SUBSTITUTE(IFERROR(INDEX(DeviceMap,MATCH($C13,INDEX(DeviceMap,0,1),0),3),""),"~",IF(OR($R13="",$R13="No Module"),"X",IFERROR(INDEX(GEMMap,MATCH($R13,INDEX(GEMMap,0,1),0),2),"X")))&"-"&$X13&"-1D") | P13: =IF($C13="","",$C13&", with ("&TEXTJOIN("/",TRUE,IF($D13="No Sensor","",$D13),IF($E13="No Sensor","",$E13),IF($F13="No Sensor","",$F13),IF($G13="No Sensor","",$G13))&")"&IF(OR($R13="",$R13="No Module"),""," + 8-gas expansion module: "&$R13)) | Q13: =IF($C13="","",IF(AND($R13<>"",$R13<>"No Module",ISERROR(SEARCH("EXO",$C13))),"Module needs EXO device",IF(OR($K13="?",NOT(ISNUMBER($M13))),"Unknown rate",IF(AND($F13<>"No Sensor",$F13=$G13),"Duplicate sensors",IF(AND($D13="No Sensor",$E13="No Sensor",$F13="No Sensor",$G13="No Sensor"),"Review: no sensors","Complete"))))) | R13: No Module | S13: =IF($C13="","",IF(OR($R13="",$R13="No Module"),0,IFERROR(INDEX(DB_Rate,MATCH(INDEX(GEMMap,MATCH($R13,INDEX(GEMMap,0,1),0),3),DB_Key,0)),0))) | T13: =CODE(IFERROR(INDEX(SensorCode,MATCH($D13,SensorName,0)),"X")) | U13: =CODE(IFERROR(INDEX(SensorCode,MATCH($E13,SensorName,0)),"X")) | V13: =CODE(IFERROR(INDEX(SensorCode,MATCH($F13,SensorName,0)),"X")) | W13: =CODE(IFERROR(INDEX(SensorCode,MATCH($G13,SensorName,0)),"X")) | X13: =CHAR(SMALL($T13:$W13,1))&CHAR(SMALL($T13:$W13,2))&CHAR(SMALL($T13:$W13,3))&CHAR(SMALL($T13:$W13,4))
B14: 7 | D14: LEL-IR | E14: O2 | F14: No Sensor | G14: No Sensor | H14: 1 | I14: =IF(ISNUMBER(Default_Days),Default_Days,1) -> 1 | J14: 0 | K14: =IF($C14="","",IFERROR(INDEX(DB_Rate,MATCH(IFERROR(INDEX(DeviceMap,MATCH($C14,INDEX(DeviceMap,0,1),0),2),""),DB_Key,0)),"?")) | L14: =IF($C14="","",IF(OR($D14="",$D14="No Sensor"),0,IF(IFERROR(INDEX(SensorTier,MATCH($D14,SensorName,0)),"Standard")="Standard",0,IFERROR(INDEX(DB_Rate,MATCH(IFERROR(INDEX(TierKeys,MATCH(IFERROR(INDEX(SensorTier,MATCH($D14,SensorName,0)),"Standard"),INDEX(TierKeys,0,1),0),2),""),DB_Key,0)),0)))+IF(OR($E14="",$E14="No Sensor"),0,IF(IFERROR(INDEX(SensorTier,MATCH($E14,SensorName,0)),"Standard")="Standard",0,IFERROR(INDEX(DB_Rate,MATCH(IFERROR(INDEX(TierKeys,MATCH(IFERROR(INDEX(SensorTier,MATCH($E14,SensorName,0)),"Standard"),INDEX(TierKeys,0,1),0),2),""),DB_Key,0)),0)))+IF(OR($F14="",$F14="No Sensor"),0,IF(IFERROR(INDEX(SensorTier,MATCH($F14,SensorName,0)),"Standard")="Standard",0,IFERROR(INDEX(DB_Rate,MATCH(IFERROR(INDEX(TierKeys,MATCH(IFERROR(INDEX(SensorTier,MATCH($F14,SensorName,0)),"Standard"),INDEX(TierKeys,0,1),0),2),""),DB_Key,0)),0)))+IF(OR($G14="",$G14="No Sensor"),0,IF(IFERROR(INDEX(SensorTier,MATCH($G14,SensorName,0)),"Standard")="Standard",0,IFERROR(INDEX(DB_Rate,MATCH(IFERROR(INDEX(TierKeys,MATCH(IFERROR(INDEX(SensorTier,MATCH($G14,SensorName,0)),"Standard"),INDEX(TierKeys,0,1),0),2),""),DB_Key,0)),0)))) | M14: =IF($C14="","",IF(ISNUMBER($K14),$K14+$L14+$S14,"")) | N14: =IF(AND($C14<>"",ISNUMBER($M14)),$H14*$I14*$M14*(1-$J14),0) -> 0 | O14: =IF($C14="","",SUBSTITUTE(IFERROR(INDEX(DeviceMap,MATCH($C14,INDEX(DeviceMap,0,1),0),3),""),"~",IF(OR($R14="",$R14="No Module"),"X",IFERROR(INDEX(GEMMap,MATCH($R14,INDEX(GEMMap,0,1),0),2),"X")))&"-"&$X14&"-1D") | P14: =IF($C14="","",$C14&", with ("&TEXTJOIN("/",TRUE,IF($D14="No Sensor","",$D14),IF($E14="No Sensor","",$E14),IF($F14="No Sensor","",$F14),IF($G14="No Sensor","",$G14))&")"&IF(OR($R14="",$R14="No Module"),""," + 8-gas expansion module: "&$R14)) | Q14: =IF($C14="","",IF(AND($R14<>"",$R14<>"No Module",ISERROR(SEARCH("EXO",$C14))),"Module needs EXO device",IF(OR($K14="?",NOT(ISNUMBER($M14))),"Unknown rate",IF(AND($F14<>"No Sensor",$F14=$G14),"Duplicate sensors",IF(AND($D14="No Sensor",$E14="No Sensor",$F14="No Sensor",$G14="No Sensor"),"Review: no sensors","Complete"))))) | R14: No Module | S14: =IF($C14="","",IF(OR($R14="",$R14="No Module"),0,IFERROR(INDEX(DB_Rate,MATCH(INDEX(GEMMap,MATCH($R14,INDEX(GEMMap,0,1),0),3),DB_Key,0)),0))) | T14: =CODE(IFERROR(INDEX(SensorCode,MATCH($D14,SensorName,0)),"X")) | U14: =CODE(IFERROR(INDEX(SensorCode,MATCH($E14,SensorName,0)),"X")) | V14: =CODE(IFERROR(INDEX(SensorCode,MATCH($F14,SensorName,0)),"X")) | W14: =CODE(IFERROR(INDEX(SensorCode,MATCH($G14,SensorName,0)),"X")) | X14: =CHAR(SMALL($T14:$W14,1))&CHAR(SMALL($T14:$W14,2))&CHAR(SMALL($T14:$W14,3))&CHAR(SMALL($T14:$W14,4))
B15: 8 | D15: LEL-IR | E15: O2 | F15: No Sensor | G15: No Sensor | H15: 1 | I15: =IF(ISNUMBER(Default_Days),Default_Days,1) -> 1 | J15: 0 | K15: =IF($C15="","",IFERROR(INDEX(DB_Rate,MATCH(IFERROR(INDEX(DeviceMap,MATCH($C15,INDEX(DeviceMap,0,1),0),2),""),DB_Key,0)),"?")) | L15: =IF($C15="","",IF(OR($D15="",$D15="No Sensor"),0,IF(IFERROR(INDEX(SensorTier,MATCH($D15,SensorName,0)),"Standard")="Standard",0,IFERROR(INDEX(DB_Rate,MATCH(IFERROR(INDEX(TierKeys,MATCH(IFERROR(INDEX(SensorTier,MATCH($D15,SensorName,0)),"Standard"),INDEX(TierKeys,0,1),0),2),""),DB_Key,0)),0)))+IF(OR($E15="",$E15="No Sensor"),0,IF(IFERROR(INDEX(SensorTier,MATCH($E15,SensorName,0)),"Standard")="Standard",0,IFERROR(INDEX(DB_Rate,MATCH(IFERROR(INDEX(TierKeys,MATCH(IFERROR(INDEX(SensorTier,MATCH($E15,SensorName,0)),"Standard"),INDEX(TierKeys,0,1),0),2),""),DB_Key,0)),0)))+IF(OR($F15="",$F15="No Sensor"),0,IF(IFERROR(INDEX(SensorTier,MATCH($F15,SensorName,0)),"Standard")="Standard",0,IFERROR(INDEX(DB_Rate,MATCH(IFERROR(INDEX(TierKeys,MATCH(IFERROR(INDEX(SensorTier,MATCH($F15,SensorName,0)),"Standard"),INDEX(TierKeys,0,1),0),2),""),DB_Key,0)),0)))+IF(OR($G15="",$G15="No Sensor"),0,IF(IFERROR(INDEX(SensorTier,MATCH($G15,SensorName,0)),"Standard")="Standard",0,IFERROR(INDEX(DB_Rate,MATCH(IFERROR(INDEX(TierKeys,MATCH(IFERROR(INDEX(SensorTier,MATCH($G15,SensorName,0)),"Standard"),INDEX(TierKeys,0,1),0),2),""),DB_Key,0)),0)))) | M15: =IF($C15="","",IF(ISNUMBER($K15),$K15+$L15+$S15,"")) | N15: =IF(AND($C15<>"",ISNUMBER($M15)),$H15*$I15*$M15*(1-$J15),0) -> 0 | O15: =IF($C15="","",SUBSTITUTE(IFERROR(INDEX(DeviceMap,MATCH($C15,INDEX(DeviceMap,0,1),0),3),""),"~",IF(OR($R15="",$R15="No Module"),"X",IFERROR(INDEX(GEMMap,MATCH($R15,INDEX(GEMMap,0,1),0),2),"X")))&"-"&$X15&"-1D") | P15: =IF($C15="","",$C15&", with ("&TEXTJOIN("/",TRUE,IF($D15="No Sensor","",$D15),IF($E15="No Sensor","",$E15),IF($F15="No Sensor","",$F15),IF($G15="No Sensor","",$G15))&")"&IF(OR($R15="",$R15="No Module"),""," + 8-gas expansion module: "&$R15)) | Q15: =IF($C15="","",IF(AND($R15<>"",$R15<>"No Module",ISERROR(SEARCH("EXO",$C15))),"Module needs EXO device",IF(OR($K15="?",NOT(ISNUMBER($M15))),"Unknown rate",IF(AND($F15<>"No Sensor",$F15=$G15),"Duplicate sensors",IF(AND($D15="No Sensor",$E15="No Sensor",$F15="No Sensor",$G15="No Sensor"),"Review: no sensors","Complete"))))) | R15: No Module | S15: =IF($C15="","",IF(OR($R15="",$R15="No Module"),0,IFERROR(INDEX(DB_Rate,MATCH(INDEX(GEMMap,MATCH($R15,INDEX(GEMMap,0,1),0),3),DB_Key,0)),0))) | T15: =CODE(IFERROR(INDEX(SensorCode,MATCH($D15,SensorName,0)),"X")) | U15: =CODE(IFERROR(INDEX(SensorCode,MATCH($E15,SensorName,0)),"X")) | V15: =CODE(IFERROR(INDEX(SensorCode,MATCH($F15,SensorName,0)),"X")) | W15: =CODE(IFERROR(INDEX(SensorCode,MATCH($G15,SensorName,0)),"X")) | X15: =CHAR(SMALL($T15:$W15,1))&CHAR(SMALL($T15:$W15,2))&CHAR(SMALL($T15:$W15,3))&CHAR(SMALL($T15:$W15,4))
B16: 9 | D16: LEL-IR | E16: O2 | F16: No Sensor | G16: No Sensor | H16: 1 | I16: =IF(ISNUMBER(Default_Days),Default_Days,1) -> 1 | J16: 0 | K16: =IF($C16="","",IFERROR(INDEX(DB_Rate,MATCH(IFERROR(INDEX(DeviceMap,MATCH($C16,INDEX(DeviceMap,0,1),0),2),""),DB_Key,0)),"?")) | L16: =IF($C16="","",IF(OR($D16="",$D16="No Sensor"),0,IF(IFERROR(INDEX(SensorTier,MATCH($D16,SensorName,0)),"Standard")="Standard",0,IFERROR(INDEX(DB_Rate,MATCH(IFERROR(INDEX(TierKeys,MATCH(IFERROR(INDEX(SensorTier,MATCH($D16,SensorName,0)),"Standard"),INDEX(TierKeys,0,1),0),2),""),DB_Key,0)),0)))+IF(OR($E16="",$E16="No Sensor"),0,IF(IFERROR(INDEX(SensorTier,MATCH($E16,SensorName,0)),"Standard")="Standard",0,IFERROR(INDEX(DB_Rate,MATCH(IFERROR(INDEX(TierKeys,MATCH(IFERROR(INDEX(SensorTier,MATCH($E16,SensorName,0)),"Standard"),INDEX(TierKeys,0,1),0),2),""),DB_Key,0)),0)))+IF(OR($F16="",$F16="No Sensor"),0,IF(IFERROR(INDEX(SensorTier,MATCH($F16,SensorName,0)),"Standard")="Standard",0,IFERROR(INDEX(DB_Rate,MATCH(IFERROR(INDEX(TierKeys,MATCH(IFERROR(INDEX(SensorTier,MATCH($F16,SensorName,0)),"Standard"),INDEX(TierKeys,0,1),0),2),""),DB_Key,0)),0)))+IF(OR($G16="",$G16="No Sensor"),0,IF(IFERROR(INDEX(SensorTier,MATCH($G16,SensorName,0)),"Standard")="Standard",0,IFERROR(INDEX(DB_Rate,MATCH(IFERROR(INDEX(TierKeys,MATCH(IFERROR(INDEX(SensorTier,MATCH($G16,SensorName,0)),"Standard"),INDEX(TierKeys,0,1),0),2),""),DB_Key,0)),0)))) | M16: =IF($C16="","",IF(ISNUMBER($K16),$K16+$L16+$S16,"")) | N16: =IF(AND($C16<>"",ISNUMBER($M16)),$H16*$I16*$M16*(1-$J16),0) -> 0 | O16: =IF($C16="","",SUBSTITUTE(IFERROR(INDEX(DeviceMap,MATCH($C16,INDEX(DeviceMap,0,1),0),3),""),"~",IF(OR($R16="",$R16="No Module"),"X",IFERROR(INDEX(GEMMap,MATCH($R16,INDEX(GEMMap,0,1),0),2),"X")))&"-"&$X16&"-1D") | P16: =IF($C16="","",$C16&", with ("&TEXTJOIN("/",TRUE,IF($D16="No Sensor","",$D16),IF($E16="No Sensor","",$E16),IF($F16="No Sensor","",$F16),IF($G16="No Sensor","",$G16))&")"&IF(OR($R16="",$R16="No Module"),""," + 8-gas expansion module: "&$R16)) | Q16: =IF($C16="","",IF(AND($R16<>"",$R16<>"No Module",ISERROR(SEARCH("EXO",$C16))),"Module needs EXO device",IF(OR($K16="?",NOT(ISNUMBER($M16))),"Unknown rate",IF(AND($F16<>"No Sensor",$F16=$G16),"Duplicate sensors",IF(AND($D16="No Sensor",$E16="No Sensor",$F16="No Sensor",$G16="No Sensor"),"Review: no sensors","Complete"))))) | R16: No Module | S16: =IF($C16="","",IF(OR($R16="",$R16="No Module"),0,IFERROR(INDEX(DB_Rate,MATCH(INDEX(GEMMap,MATCH($R16,INDEX(GEMMap,0,1),0),3),DB_Key,0)),0))) | T16: =CODE(IFERROR(INDEX(SensorCode,MATCH($D16,SensorName,0)),"X")) | U16: =CODE(IFERROR(INDEX(SensorCode,MATCH($E16,SensorName,0)),"X")) | V16: =CODE(IFERROR(INDEX(SensorCode,MATCH($F16,SensorName,0)),"X")) | W16: =CODE(IFERROR(INDEX(SensorCode,MATCH($G16,SensorName,0)),"X")) | X16: =CHAR(SMALL($T16:$W16,1))&CHAR(SMALL($T16:$W16,2))&CHAR(SMALL($T16:$W16,3))&CHAR(SMALL($T16:$W16,4))
B17: 10 | D17: LEL-IR | E17: O2 | F17: No Sensor | G17: No Sensor | H17: 1 | I17: =IF(ISNUMBER(Default_Days),Default_Days,1) -> 1 | J17: 0 | K17: =IF($C17="","",IFERROR(INDEX(DB_Rate,MATCH(IFERROR(INDEX(DeviceMap,MATCH($C17,INDEX(DeviceMap,0,1),0),2),""),DB_Key,0)),"?")) | L17: =IF($C17="","",IF(OR($D17="",$D17="No Sensor"),0,IF(IFERROR(INDEX(SensorTier,MATCH($D17,SensorName,0)),"Standard")="Standard",0,IFERROR(INDEX(DB_Rate,MATCH(IFERROR(INDEX(TierKeys,MATCH(IFERROR(INDEX(SensorTier,MATCH($D17,SensorName,0)),"Standard"),INDEX(TierKeys,0,1),0),2),""),DB_Key,0)),0)))+IF(OR($E17="",$E17="No Sensor"),0,IF(IFERROR(INDEX(SensorTier,MATCH($E17,SensorName,0)),"Standard")="Standard",0,IFERROR(INDEX(DB_Rate,MATCH(IFERROR(INDEX(TierKeys,MATCH(IFERROR(INDEX(SensorTier,MATCH($E17,SensorName,0)),"Standard"),INDEX(TierKeys,0,1),0),2),""),DB_Key,0)),0)))+IF(OR($F17="",$F17="No Sensor"),0,IF(IFERROR(INDEX(SensorTier,MATCH($F17,SensorName,0)),"Standard")="Standard",0,IFERROR(INDEX(DB_Rate,MATCH(IFERROR(INDEX(TierKeys,MATCH(IFERROR(INDEX(SensorTier,MATCH($F17,SensorName,0)),"Standard"),INDEX(TierKeys,0,1),0),2),""),DB_Key,0)),0)))+IF(OR($G17="",$G17="No Sensor"),0,IF(IFERROR(INDEX(SensorTier,MATCH($G17,SensorName,0)),"Standard")="Standard",0,IFERROR(INDEX(DB_Rate,MATCH(IFERROR(INDEX(TierKeys,MATCH(IFERROR(INDEX(SensorTier,MATCH($G17,SensorName,0)),"Standard"),INDEX(TierKeys,0,1),0),2),""),DB_Key,0)),0)))) | M17: =IF($C17="","",IF(ISNUMBER($K17),$K17+$L17+$S17,"")) | N17: =IF(AND($C17<>"",ISNUMBER($M17)),$H17*$I17*$M17*(1-$J17),0) -> 0 | O17: =IF($C17="","",SUBSTITUTE(IFERROR(INDEX(DeviceMap,MATCH($C17,INDEX(DeviceMap,0,1),0),3),""),"~",IF(OR($R17="",$R17="No Module"),"X",IFERROR(INDEX(GEMMap,MATCH($R17,INDEX(GEMMap,0,1),0),2),"X")))&"-"&$X17&"-1D") | P17: =IF($C17="","",$C17&", with ("&TEXTJOIN("/",TRUE,IF($D17="No Sensor","",$D17),IF($E17="No Sensor","",$E17),IF($F17="No Sensor","",$F17),IF($G17="No Sensor","",$G17))&")"&IF(OR($R17="",$R17="No Module"),""," + 8-gas expansion module: "&$R17)) | Q17: =IF($C17="","",IF(AND($R17<>"",$R17<>"No Module",ISERROR(SEARCH("EXO",$C17))),"Module needs EXO device",IF(OR($K17="?",NOT(ISNUMBER($M17))),"Unknown rate",IF(AND($F17<>"No Sensor",$F17=$G17),"Duplicate sensors",IF(AND($D17="No Sensor",$E17="No Sensor",$F17="No Sensor",$G17="No Sensor"),"Review: no sensors","Complete"))))) | R17: No Module | S17: =IF($C17="","",IF(OR($R17="",$R17="No Module"),0,IFERROR(INDEX(DB_Rate,MATCH(INDEX(GEMMap,MATCH($R17,INDEX(GEMMap,0,1),0),3),DB_Key,0)),0))) | T17: =CODE(IFERROR(INDEX(SensorCode,MATCH($D17,SensorName,0)),"X")) | U17: =CODE(IFERROR(INDEX(SensorCode,MATCH($E17,SensorName,0)),"X")) | V17: =CODE(IFERROR(INDEX(SensorCode,MATCH($F17,SensorName,0)),"X")) | W17: =CODE(IFERROR(INDEX(SensorCode,MATCH($G17,SensorName,0)),"X")) | X17: =CHAR(SMALL($T17:$W17,1))&CHAR(SMALL($T17:$W17,2))&CHAR(SMALL($T17:$W17,3))&CHAR(SMALL($T17:$W17,4))
M19: Configured Equipment Subtotal | N19: =SUM(N8:N17) -> 0

Sheet Accessories & Services
B2: ACCESSORIES & SERVICES
B3: Add G7/EXO accessories, bridges, services, monitoring, consumables, calibration gas and training. All rates from USD List column C. Choose Daily or One-Time. Use Rate Override for blank/manual-rate lines.
B5: Include | C5: SKU | D5: Description | E5: Category | F5: Method | G5: Qty | H5: Days | I5: Daily Rate | J5: Rate Override | K5: Eff. Rate | L5: Disc % | M5: Extended | N5: Notes
B6: No | C6: RENT-BEACON | D6: =IF($C6="","",IFERROR(INDEX(DB_Desc,MATCH($C6,DB_Key,0)),"** SKU not found **")) -> Rental service, beacon, daily rate | E6: =IF($C6="","",IFERROR(INDEX(DB_Cat,MATCH($C6,DB_Key,0)),"")) -> G7 Accessories | F6: Daily | G6: 1 | H6: =IF(ISNUMBER(Default_Days),Default_Days,1) -> 1 | I6: =IF($C6="","",IFERROR(INDEX(DB_Rate,MATCH($C6,DB_Key,0)),"")) -> 2.4 | K6: =IF($C6="","",IF(ISNUMBER($J6),$J6,IF(ISNUMBER($I6),$I6,""))) -> 2.4 | L6: 0 | M6: =IF(AND($B6="Yes",$C6<>"",ISNUMBER($K6)),IF($F6="One-Time",$G6*$K6*(1-$L6),$G6*$H6*$K6*(1-$L6)),0) -> 0
B7: No | C7: RENT-TRAIN | D7: =IF($C7="","",IFERROR(INDEX(DB_Desc,MATCH($C7,DB_Key,0)),"** SKU not found **")) -> Training, Daily, at Blackline Facility | E7: =IF($C7="","",IFERROR(INDEX(DB_Cat,MATCH($C7,DB_Key,0)),"")) -> Additional Services | F7: Daily | G7: 1 | H7: =IF(ISNUMBER(Default_Days),Default_Days,1) -> 1 | I7: =IF($C7="","",IFERROR(INDEX(DB_Rate,MATCH($C7,DB_Key,0)),"")) -> 1000 | K7: =IF($C7="","",IF(ISNUMBER($J7),$J7,IF(ISNUMBER($I7),$I7,""))) -> 1000 | L7: 0 | M7: =IF(AND($B7="Yes",$C7<>"",ISNUMBER($K7)),IF($F7="One-Time",$G7*$K7*(1-$L7),$G7*$H7*$K7*(1-$L7)),0) -> 0
B8: No | C8: RENTAL-ONE-TIME | D8: =IF($C8="","",IFERROR(INDEX(DB_Desc,MATCH($C8,DB_Key,0)),"** SKU not found **")) -> One time charge - as needed [MANUAL PRICE REQUIRED] | E8: =IF($C8="","",IFERROR(INDEX(DB_Cat,MATCH($C8,DB_Key,0)),"")) -> Additional Services | F8: Daily | G8: 1 | H8: =IF(ISNUMBER(Default_Days),Default_Days,1) -> 1 | I8: =IF($C8="","",IFERROR(INDEX(DB_Rate,MATCH($C8,DB_Key,0)),"")) -> 0 | J8: 300 | K8: =IF($C8="","",IF(ISNUMBER($J8),$J8,IF(ISNUMBER($I8),$I8,""))) -> 300 | L8: 0 | M8: =IF(AND($B8="Yes",$C8<>"",ISNUMBER($K8)),IF($F8="One-Time",$G8*$K8*(1-$L8),$G8*$H8*$K8*(1-$L8)),0) -> 0
B9: No | D9: =IF($C9="","",IFERROR(INDEX(DB_Desc,MATCH($C9,DB_Key,0)),"** SKU not found **")) | E9: =IF($C9="","",IFERROR(INDEX(DB_Cat,MATCH($C9,DB_Key,0)),"")) | F9: Daily | G9: 1 | H9: =IF(ISNUMBER(Default_Days),Default_Days,1) -> 1 | I9: =IF($C9="","",IFERROR(INDEX(DB_Rate,MATCH($C9,DB_Key,0)),"")) | K9: =IF($C9="","",IF(ISNUMBER($J9),$J9,IF(ISNUMBER($I9),$I9,""))) | L9: 0 | M9: =IF(AND($B9="Yes",$C9<>"",ISNUMBER($K9)),IF($F9="One-Time",$G9*$K9*(1-$L9),$G9*$H9*$K9*(1-$L9)),0) -> 0
B10: No | D10: =IF($C10="","",IFERROR(INDEX(DB_Desc,MATCH($C10,DB_Key,0)),"** SKU not found **")) | E10: =IF($C10="","",IFERROR(INDEX(DB_Cat,MATCH($C10,DB_Key,0)),"")) | F10: Daily | G10: 1 | H10: =IF(ISNUMBER(Default_Days),Default_Days,1) -> 1 | I10: =IF($C10="","",IFERROR(INDEX(DB_Rate,MATCH($C10,DB_Key,0)),"")) | K10: =IF($C10="","",IF(ISNUMBER($J10),$J10,IF(ISNUMBER($I10),$I10,""))) | L10: 0 | M10: =IF(AND($B10="Yes",$C10<>"",ISNUMBER($K10)),IF($F10="One-Time",$G10*$K10*(1-$L10),$G10*$H10*$K10*(1-$L10)),0) -> 0
B11: No | D11: =IF($C11="","",IFERROR(INDEX(DB_Desc,MATCH($C11,DB_Key,0)),"** SKU not found **")) | E11: =IF($C11="","",IFERROR(INDEX(DB_Cat,MATCH($C11,DB_Key,0)),"")) | F11: Daily | G11: 1 | H11: =IF(ISNUMBER(Default_Days),Default_Days,1) -> 1 | I11: =IF($C11="","",IFERROR(INDEX(DB_Rate,MATCH($C11,DB_Key,0)),"")) | K11: =IF($C11="","",IF(ISNUMBER($J11),$J11,IF(ISNUMBER($I11),$I11,""))) | L11: 0 | M11: =IF(AND($B11="Yes",$C11<>"",ISNUMBER($K11)),IF($F11="One-Time",$G11*$K11*(1-$L11),$G11*$H11*$K11*(1-$L11)),0) -> 0
B12: No | D12: =IF($C12="","",IFERROR(INDEX(DB_Desc,MATCH($C12,DB_Key,0)),"** SKU not found **")) | E12: =IF($C12="","",IFERROR(INDEX(DB_Cat,MATCH($C12,DB_Key,0)),"")) | F12: Daily | G12: 1 | H12: =IF(ISNUMBER(Default_Days),Default_Days,1) -> 1 | I12: =IF($C12="","",IFERROR(INDEX(DB_Rate,MATCH($C12,DB_Key,0)),"")) | K12: =IF($C12="","",IF(ISNUMBER($J12),$J12,IF(ISNUMBER($I12),$I12,""))) | L12: 0 | M12: =IF(AND($B12="Yes",$C12<>"",ISNUMBER($K12)),IF($F12="One-Time",$G12*$K12*(1-$L12),$G12*$H12*$K12*(1-$L12)),0) -> 0
B13: No | D13: =IF($C13="","",IFERROR(INDEX(DB_Desc,MATCH($C13,DB_Key,0)),"** SKU not found **")) | E13: =IF($C13="","",IFERROR(INDEX(DB_Cat,MATCH($C13,DB_Key,0)),"")) | F13: Daily | G13: 1 | H13: =IF(ISNUMBER(Default_Days),Default_Days,1) -> 1 | I13: =IF($C13="","",IFERROR(INDEX(DB_Rate,MATCH($C13,DB_Key,0)),"")) | K13: =IF($C13="","",IF(ISNUMBER($J13),$J13,IF(ISNUMBER($I13),$I13,""))) | L13: 0 | M13: =IF(AND($B13="Yes",$C13<>"",ISNUMBER($K13)),IF($F13="One-Time",$G13*$K13*(1-$L13),$G13*$H13*$K13*(1-$L13)),0) -> 0
B14: No | D14: =IF($C14="","",IFERROR(INDEX(DB_Desc,MATCH($C14,DB_Key,0)),"** SKU not found **")) | E14: =IF($C14="","",IFERROR(INDEX(DB_Cat,MATCH($C14,DB_Key,0)),"")) | F14: Daily | G14: 1 | H14: =IF(ISNUMBER(Default_Days),Default_Days,1) -> 1 | I14: =IF($C14="","",IFERROR(INDEX(DB_Rate,MATCH($C14,DB_Key,0)),"")) | K14: =IF($C14="","",IF(ISNUMBER($J14),$J14,IF(ISNUMBER($I14),$I14,""))) | L14: 0 | M14: =IF(AND($B14="Yes",$C14<>"",ISNUMBER($K14)),IF($F14="One-Time",$G14*$K14*(1-$L14),$G14*$H14*$K14*(1-$L14)),0) -> 0
B15: No | D15: =IF($C15="","",IFERROR(INDEX(DB_Desc,MATCH($C15,DB_Key,0)),"** SKU not found **")) | E15: =IF($C15="","",IFERROR(INDEX(DB_Cat,MATCH($C15,DB_Key,0)),"")) | F15: Daily | G15: 1 | H15: =IF(ISNUMBER(Default_Days),Default_Days,1) -> 1 | I15: =IF($C15="","",IFERROR(INDEX(DB_Rate,MATCH($C15,DB_Key,0)),"")) | K15: =IF($C15="","",IF(ISNUMBER($J15),$J15,IF(ISNUMBER($I15),$I15,""))) | L15: 0 | M15: =IF(AND($B15="Yes",$C15<>"",ISNUMBER($K15)),IF($F15="One-Time",$G15*$K15*(1-$L15),$G15*$H15*$K15*(1-$L15)),0) -> 0
B16: No | D16: =IF($C16="","",IFERROR(INDEX(DB_Desc,MATCH($C16,DB_Key,0)),"** SKU not found **")) | E16: =IF($C16="","",IFERROR(INDEX(DB_Cat,MATCH($C16,DB_Key,0)),"")) | F16: Daily | G16: 1 | H16: =IF(ISNUMBER(Default_Days),Default_Days,1) -> 1 | I16: =IF($C16="","",IFERROR(INDEX(DB_Rate,MATCH($C16,DB_Key,0)),"")) | K16: =IF($C16="","",IF(ISNUMBER($J16),$J16,IF(ISNUMBER($I16),$I16,""))) | L16: 0 | M16: =IF(AND($B16="Yes",$C16<>"",ISNUMBER($K16)),IF($F16="One-Time",$G16*$K16*(1-$L16),$G16*$H16*$K16*(1-$L16)),0) -> 0
B17: No | D17: =IF($C17="","",IFERROR(INDEX(DB_Desc,MATCH($C17,DB_Key,0)),"** SKU not found **")) | E17: =IF($C17="","",IFERROR(INDEX(DB_Cat,MATCH($C17,DB_Key,0)),"")) | F17: Daily | G17: 1 | H17: =IF(ISNUMBER(Default_Days),Default_Days,1) -> 1 | I17: =IF($C17="","",IFERROR(INDEX(DB_Rate,MATCH($C17,DB_Key,0)),"")) | K17: =IF($C17="","",IF(ISNUMBER($J17),$J17,IF(ISNUMBER($I17),$I17,""))) | L17: 0 | M17: =IF(AND($B17="Yes",$C17<>"",ISNUMBER($K17)),IF($F17="One-Time",$G17*$K17*(1-$L17),$G17*$H17*$K17*(1-$L17)),0) -> 0
B18: No | D18: =IF($C18="","",IFERROR(INDEX(DB_Desc,MATCH($C18,DB_Key,0)),"** SKU not found **")) | E18: =IF($C18="","",IFERROR(INDEX(DB_Cat,MATCH($C18,DB_Key,0)),"")) | F18: Daily | G18: 1 | H18: =IF(ISNUMBER(Default_Days),Default_Days,1) -> 1 | I18: =IF($C18="","",IFERROR(INDEX(DB_Rate,MATCH($C18,DB_Key,0)),"")) | K18: =IF($C18="","",IF(ISNUMBER($J18),$J18,IF(ISNUMBER($I18),$I18,""))) | L18: 0 | M18: =IF(AND($B18="Yes",$C18<>"",ISNUMBER($K18)),IF($F18="One-Time",$G18*$K18*(1-$L18),$G18*$H18*$K18*(1-$L18)),0) -> 0
B19: No | D19: =IF($C19="","",IFERROR(INDEX(DB_Desc,MATCH($C19,DB_Key,0)),"** SKU not found **")) | E19: =IF($C19="","",IFERROR(INDEX(DB_Cat,MATCH($C19,DB_Key,0)),"")) | F19: Daily | G19: 1 | H19: =IF(ISNUMBER(Default_Days),Default_Days,1) -> 1 | I19: =IF($C19="","",IFERROR(INDEX(DB_Rate,MATCH($C19,DB_Key,0)),"")) | K19: =IF($C19="","",IF(ISNUMBER($J19),$J19,IF(ISNUMBER($I19),$I19,""))) | L19: 0 | M19: =IF(AND($B19="Yes",$C19<>"",ISNUMBER($K19)),IF($F19="One-Time",$G19*$K19*(1-$L19),$G19*$H19*$K19*(1-$L19)),0) -> 0
B20: No | D20: =IF($C20="","",IFERROR(INDEX(DB_Desc,MATCH($C20,DB_Key,0)),"** SKU not found **")) | E20: =IF($C20="","",IFERROR(INDEX(DB_Cat,MATCH($C20,DB_Key,0)),"")) | F20: Daily | G20: 1 | H20: =IF(ISNUMBER(Default_Days),Default_Days,1) -> 1 | I20: =IF($C20="","",IFERROR(INDEX(DB_Rate,MATCH($C20,DB_Key,0)),"")) | K20: =IF($C20="","",IF(ISNUMBER($J20),$J20,IF(ISNUMBER($I20),$I20,""))) | L20: 0 | M20: =IF(AND($B20="Yes",$C20<>"",ISNUMBER($K20)),IF($F20="One-Time",$G20*$K20*(1-$L20),$G20*$H20*$K20*(1-$L20)),0) -> 0
... B33: No | D33: =IF($C33="","",IFERROR(INDEX(DB_Desc,MATCH($C33,DB_Key,0)),"** SKU not found **")) | E33: =IF($C33="","",IFERROR(INDEX(DB_Cat,MATCH($C33,DB_Key,0)),"")) | F33: Daily | G33: 1 | H33: =IF(ISNUMBER(Default_Days),Default_Days,1) -> 1 | I33: =IF($C33="","",IFERROR(INDEX(DB_Rate,MATCH($C33,DB_Key,0)),"")) | K33: =IF($C33="","",IF(ISNUMBER($J33),$J33,IF(ISNUMBER($I33),$I33,""))) | L33: 0 | M33: =IF(AND($B33="Yes",$C33<>"",ISNUMBER($K33)),IF($F33="One-Time",$G33*$K33*(1-$L33),$G33*$H33*$K33*(1-$L33)),0) -> 0
L35: Accessories Subtotal | M35: =SUM(M6:M33) -> 0

Sheet Quote Summary
B2: QUOTE SUMMARY (INTERNAL)
B3: Consolidated view of configured equipment and add-ons with totals.
B5: =IF(Quote_Number="","Quote #: (enter on Start Quote)","Quote #: "&Quote_Number) -> Quote #: (enter on Start Quote)
B6: =IF(Cust_Company="","Customer: -","Customer: "&Cust_Company) -> Customer: -
B8: Configuration | C8: Code | D8: Qty | E8: Unit Daily | F8: Extended
B9: =IF(ISNUMBER(MATCH(1,CfgRank,0)),INDEX('Guided Configurator'!$P:$P,INDEX(CfgRankRow,MATCH(1,CfgRank,0))),"") | C9: =IF(ISNUMBER(MATCH(1,CfgRank,0)),INDEX('Guided Configurator'!$O:$O,INDEX(CfgRankRow,MATCH(1,CfgRank,0))),"") | D9: =IF(ISNUMBER(MATCH(1,CfgRank,0)),INDEX('Guided Configurator'!$H:$H,INDEX(CfgRankRow,MATCH(1,CfgRank,0))),"") | E9: =IF(ISNUMBER(MATCH(1,CfgRank,0)),INDEX('Guided Configurator'!$M:$M,INDEX(CfgRankRow,MATCH(1,CfgRank,0))),"") | F9: =IF(ISNUMBER(MATCH(1,CfgRank,0)),INDEX('Guided Configurator'!$N:$N,INDEX(CfgRankRow,MATCH(1,CfgRank,0))),"")
B10: =IF(ISNUMBER(MATCH(2,CfgRank,0)),INDEX('Guided Configurator'!$P:$P,INDEX(CfgRankRow,MATCH(2,CfgRank,0))),"") | C10: =IF(ISNUMBER(MATCH(2,CfgRank,0)),INDEX('Guided Configurator'!$O:$O,INDEX(CfgRankRow,MATCH(2,CfgRank,0))),"") | D10: =IF(ISNUMBER(MATCH(2,CfgRank,0)),INDEX('Guided Configurator'!$H:$H,INDEX(CfgRankRow,MATCH(2,CfgRank,0))),"") | E10: =IF(ISNUMBER(MATCH(2,CfgRank,0)),INDEX('Guided Configurator'!$M:$M,INDEX(CfgRankRow,MATCH(2,CfgRank,0))),"") | F10: =IF(ISNUMBER(MATCH(2,CfgRank,0)),INDEX('Guided Configurator'!$N:$N,INDEX(CfgRankRow,MATCH(2,CfgRank,0))),"")
B11: =IF(ISNUMBER(MATCH(3,CfgRank,0)),INDEX('Guided Configurator'!$P:$P,INDEX(CfgRankRow,MATCH(3,CfgRank,0))),"") | C11: =IF(ISNUMBER(MATCH(3,CfgRank,0)),INDEX('Guided Configurator'!$O:$O,INDEX(CfgRankRow,MATCH(3,CfgRank,0))),"") | D11: =IF(ISNUMBER(MATCH(3,CfgRank,0)),INDEX('Guided Configurator'!$H:$H,INDEX(CfgRankRow,MATCH(3,CfgRank,0))),"") | E11: =IF(ISNUMBER(MATCH(3,CfgRank,0)),INDEX('Guided Configurator'!$M:$M,INDEX(CfgRankRow,MATCH(3,CfgRank,0))),"") | F11: =IF(ISNUMBER(MATCH(3,CfgRank,0)),INDEX('Guided Configurator'!$N:$N,INDEX(CfgRankRow,MATCH(3,CfgRank,0))),"")
B12: =IF(ISNUMBER(MATCH(4,CfgRank,0)),INDEX('Guided Configurator'!$P:$P,INDEX(CfgRankRow,MATCH(4,CfgRank,0))),"") | C12: =IF(ISNUMBER(MATCH(4,CfgRank,0)),INDEX('Guided Configurator'!$O:$O,INDEX(CfgRankRow,MATCH(4,CfgRank,0))),"") | D12: =IF(ISNUMBER(MATCH(4,CfgRank,0)),INDEX('Guided Configurator'!$H:$H,INDEX(CfgRankRow,MATCH(4,CfgRank,0))),"") | E12: =IF(ISNUMBER(MATCH(4,CfgRank,0)),INDEX('Guided Configurator'!$M:$M,INDEX(CfgRankRow,MATCH(4,CfgRank,0))),"") | F12: =IF(ISNUMBER(MATCH(4,CfgRank,0)),INDEX('Guided Configurator'!$N:$N,INDEX(CfgRankRow,MATCH(4,CfgRank,0))),"")
B13: =IF(ISNUMBER(MATCH(5,CfgRank,0)),INDEX('Guided Configurator'!$P:$P,INDEX(CfgRankRow,MATCH(5,CfgRank,0))),"") | C13: =IF(ISNUMBER(MATCH(5,CfgRank,0)),INDEX('Guided Configurator'!$O:$O,INDEX(CfgRankRow,MATCH(5,CfgRank,0))),"") | D13: =IF(ISNUMBER(MATCH(5,CfgRank,0)),INDEX('Guided Configurator'!$H:$H,INDEX(CfgRankRow,MATCH(5,CfgRank,0))),"") | E13: =IF(ISNUMBER(MATCH(5,CfgRank,0)),INDEX('Guided Configurator'!$M:$M,INDEX(CfgRankRow,MATCH(5,CfgRank,0))),"") | F13: =IF(ISNUMBER(MATCH(5,CfgRank,0)),INDEX('Guided Configurator'!$N:$N,INDEX(CfgRankRow,MATCH(5,CfgRank,0))),"")
B14: =IF(ISNUMBER(MATCH(6,CfgRank,0)),INDEX('Guided Configurator'!$P:$P,INDEX(CfgRankRow,MATCH(6,CfgRank,0))),"") | C14: =IF(ISNUMBER(MATCH(6,CfgRank,0)),INDEX('Guided Configurator'!$O:$O,INDEX(CfgRankRow,MATCH(6,CfgRank,0))),"") | D14: =IF(ISNUMBER(MATCH(6,CfgRank,0)),INDEX('Guided Configurator'!$H:$H,INDEX(CfgRankRow,MATCH(6,CfgRank,0))),"") | E14: =IF(ISNUMBER(MATCH(6,CfgRank,0)),INDEX('Guided Configurator'!$M:$M,INDEX(CfgRankRow,MATCH(6,CfgRank,0))),"") | F14: =IF(ISNUMBER(MATCH(6,CfgRank,0)),INDEX('Guided Configurator'!$N:$N,INDEX(CfgRankRow,MATCH(6,CfgRank,0))),"")
B15: =IF(ISNUMBER(MATCH(7,CfgRank,0)),INDEX('Guided Configurator'!$P:$P,INDEX(CfgRankRow,MATCH(7,CfgRank,0))),"") | C15: =IF(ISNUMBER(MATCH(7,CfgRank,0)),INDEX('Guided Configurator'!$O:$O,INDEX(CfgRankRow,MATCH(7,CfgRank,0))),"") | D15: =IF(ISNUMBER(MATCH(7,CfgRank,0)),INDEX('Guided Configurator'!$H:$H,INDEX(CfgRankRow,MATCH(7,CfgRank,0))),"") | E15: =IF(ISNUMBER(MATCH(7,CfgRank,0)),INDEX('Guided Configurator'!$M:$M,INDEX(CfgRankRow,MATCH(7,CfgRank,0))),"") | F15: =IF(ISNUMBER(MATCH(7,CfgRank,0)),INDEX('Guided Configurator'!$N:$N,INDEX(CfgRankRow,MATCH(7,CfgRank,0))),"")
B16: =IF(ISNUMBER(MATCH(8,CfgRank,0)),INDEX('Guided Configurator'!$P:$P,INDEX(CfgRankRow,MATCH(8,CfgRank,0))),"") | C16: =IF(ISNUMBER(MATCH(8,CfgRank,0)),INDEX('Guided Configurator'!$O:$O,INDEX(CfgRankRow,MATCH(8,CfgRank,0))),"") | D16: =IF(ISNUMBER(MATCH(8,CfgRank,0)),INDEX('Guided Configurator'!$H:$H,INDEX(CfgRankRow,MATCH(8,CfgRank,0))),"") | E16: =IF(ISNUMBER(MATCH(8,CfgRank,0)),INDEX('Guided Configurator'!$M:$M,INDEX(CfgRankRow,MATCH(8,CfgRank,0))),"") | F16: =IF(ISNUMBER(MATCH(8,CfgRank,0)),INDEX('Guided Configurator'!$N:$N,INDEX(CfgRankRow,MATCH(8,CfgRank,0))),"")
B17: =IF(ISNUMBER(MATCH(9,CfgRank,0)),INDEX('Guided Configurator'!$P:$P,INDEX(CfgRankRow,MATCH(9,CfgRank,0))),"") | C17: =IF(ISNUMBER(MATCH(9,CfgRank,0)),INDEX('Guided Configurator'!$O:$O,INDEX(CfgRankRow,MATCH(9,CfgRank,0))),"") | D17: =IF(ISNUMBER(MATCH(9,CfgRank,0)),INDEX('Guided Configurator'!$H:$H,INDEX(CfgRankRow,MATCH(9,CfgRank,0))),"") | E17: =IF(ISNUMBER(MATCH(9,CfgRank,0)),INDEX('Guided Configurator'!$M:$M,INDEX(CfgRankRow,MATCH(9,CfgRank,0))),"") | F17: =IF(ISNUMBER(MATCH(9,CfgRank,0)),INDEX('Guided Configurator'!$N:$N,INDEX(CfgRankRow,MATCH(9,CfgRank,0))),"")
B18: =IF(ISNUMBER(MATCH(10,CfgRank,0)),INDEX('Guided Configurator'!$P:$P,INDEX(CfgRankRow,MATCH(10,CfgRank,0))),"") | C18: =IF(ISNUMBER(MATCH(10,CfgRank,0)),INDEX('Guided Configurator'!$O:$O,INDEX(CfgRankRow,MATCH(10,CfgRank,0))),"") | D18: =IF(ISNUMBER(MATCH(10,CfgRank,0)),INDEX('Guided Configurator'!$H:$H,INDEX(CfgRankRow,MATCH(10,CfgRank,0))),"") | E18: =IF(ISNUMBER(MATCH(10,CfgRank,0)),INDEX('Guided Configurator'!$M:$M,INDEX(CfgRankRow,MATCH(10,CfgRank,0))),"") | F18: =IF(ISNUMBER(MATCH(10,CfgRank,0)),INDEX('Guided Configurator'!$N:$N,INDEX(CfgRankRow,MATCH(10,CfgRank,0))),"")
E19: Configured Equipment Subtotal | F19: =Config_Subtotal -> 0
B21: Accessories & Services | E21: Subtotal | F21: =Acc_Subtotal -> 0
E23: Subtotal | F23: =Quote_Subtotal -> 0
E24: Freight | F24: =Freight -> 0
E25: Miscellaneous | F25: =Misc_Charge -> 0
E26: =CONCATENATE("Tax (",TEXT(Tax_Rate,"0.0%"),")") -> Tax (0.0%) | F26: =ROUND(Quote_Subtotal*Tax_Rate,2) -> 0
D27: GRAND TOTAL | F27: =Quote_GrandTotal -> 0

Sheet Printable Quote
B2: RENTAL QUOTATION
B3: Gas Detection Equipment Rental — 2026 Pricing
B5: Quote Number | C5: =IF(Quote_Number="","",Quote_Number) | F5: Customer | G5: =IF(Cust_Company="","",Cust_Company)
B6: Quote Date | C6: =IF(ISNUMBER(Quote_Date),TEXT(Quote_Date,"mmm d, yyyy"),"") | F6: Contact | G6: =IF(Cust_Contact="","",Cust_Contact)
B7: Valid Through | C7: =IF(ISNUMBER(Valid_Through),TEXT(Valid_Through,"mmm d, yyyy"),"") | F7: Email / Phone | G7: =IF(AND(Cust_Email="",Cust_Phone=""),"",Cust_Email&IF(AND(Cust_Email<>"",Cust_Phone<>"")," | ","")&Cust_Phone)
B8: Salesperson | C8: =IF(Salesperson="","",Salesperson) | F8: Project / Site | G8: =IF(Cust_Project="","",Cust_Project)
B10: =IF(AND(ISNUMBER(Rental_Start),ISNUMBER(Rental_End)),"Rental Period: "&TEXT(Rental_Start,"mmm d, yyyy")&" to "&TEXT(Rental_End,"mmm d, yyyy")&" ("&Default_Days&" days)","")
B12: CONFIGURED EQUIPMENT
B13: Config Code | C13: Configuration | D13: Qty | E13: Days | F13: Unit Daily | G13: Disc | H13: Amount
B14: =IF(ISNUMBER(MATCH(1,CfgRank,0)),INDEX('Guided Configurator'!$O:$O,INDEX(CfgRankRow,MATCH(1,CfgRank,0))),"") | C14: =IF(ISNUMBER(MATCH(1,CfgRank,0)),INDEX('Guided Configurator'!$P:$P,INDEX(CfgRankRow,MATCH(1,CfgRank,0))),"") | D14: =IF(ISNUMBER(MATCH(1,CfgRank,0)),INDEX('Guided Configurator'!$H:$H,INDEX(CfgRankRow,MATCH(1,CfgRank,0))),"") | E14: =IF(ISNUMBER(MATCH(1,CfgRank,0)),INDEX('Guided Configurator'!$I:$I,INDEX(CfgRankRow,MATCH(1,CfgRank,0))),"") | F14: =IF(ISNUMBER(MATCH(1,CfgRank,0)),INDEX('Guided Configurator'!$M:$M,INDEX(CfgRankRow,MATCH(1,CfgRank,0))),"") | G14: =IF(ISNUMBER(MATCH(1,CfgRank,0)),INDEX('Guided Configurator'!$J:$J,INDEX(CfgRankRow,MATCH(1,CfgRank,0))),"") | H14: =IF(ISNUMBER(MATCH(1,CfgRank,0)),INDEX('Guided Configurator'!$N:$N,INDEX(CfgRankRow,MATCH(1,CfgRank,0))),"")
B15: =IF(ISNUMBER(MATCH(2,CfgRank,0)),INDEX('Guided Configurator'!$O:$O,INDEX(CfgRankRow,MATCH(2,CfgRank,0))),"") | C15: =IF(ISNUMBER(MATCH(2,CfgRank,0)),INDEX('Guided Configurator'!$P:$P,INDEX(CfgRankRow,MATCH(2,CfgRank,0))),"") | D15: =IF(ISNUMBER(MATCH(2,CfgRank,0)),INDEX('Guided Configurator'!$H:$H,INDEX(CfgRankRow,MATCH(2,CfgRank,0))),"") | E15: =IF(ISNUMBER(MATCH(2,CfgRank,0)),INDEX('Guided Configurator'!$I:$I,INDEX(CfgRankRow,MATCH(2,CfgRank,0))),"") | F15: =IF(ISNUMBER(MATCH(2,CfgRank,0)),INDEX('Guided Configurator'!$M:$M,INDEX(CfgRankRow,MATCH(2,CfgRank,0))),"") | G15: =IF(ISNUMBER(MATCH(2,CfgRank,0)),INDEX('Guided Configurator'!$J:$J,INDEX(CfgRankRow,MATCH(2,CfgRank,0))),"") | H15: =IF(ISNUMBER(MATCH(2,CfgRank,0)),INDEX('Guided Configurator'!$N:$N,INDEX(CfgRankRow,MATCH(2,CfgRank,0))),"")
B16: =IF(ISNUMBER(MATCH(3,CfgRank,0)),INDEX('Guided Configurator'!$O:$O,INDEX(CfgRankRow,MATCH(3,CfgRank,0))),"") | C16: =IF(ISNUMBER(MATCH(3,CfgRank,0)),INDEX('Guided Configurator'!$P:$P,INDEX(CfgRankRow,MATCH(3,CfgRank,0))),"") | D16: =IF(ISNUMBER(MATCH(3,CfgRank,0)),INDEX('Guided Configurator'!$H:$H,INDEX(CfgRankRow,MATCH(3,CfgRank,0))),"") | E16: =IF(ISNUMBER(MATCH(3,CfgRank,0)),INDEX('Guided Configurator'!$I:$I,INDEX(CfgRankRow,MATCH(3,CfgRank,0))),"") | F16: =IF(ISNUMBER(MATCH(3,CfgRank,0)),INDEX('Guided Configurator'!$M:$M,INDEX(CfgRankRow,MATCH(3,CfgRank,0))),"") | G16: =IF(ISNUMBER(MATCH(3,CfgRank,0)),INDEX('Guided Configurator'!$J:$J,INDEX(CfgRankRow,MATCH(3,CfgRank,0))),"") | H16: =IF(ISNUMBER(MATCH(3,CfgRank,0)),INDEX('Guided Configurator'!$N:$N,INDEX(CfgRankRow,MATCH(3,CfgRank,0))),"")
B17: =IF(ISNUMBER(MATCH(4,CfgRank,0)),INDEX('Guided Configurator'!$O:$O,INDEX(CfgRankRow,MATCH(4,CfgRank,0))),"") | C17: =IF(ISNUMBER(MATCH(4,CfgRank,0)),INDEX('Guided Configurator'!$P:$P,INDEX(CfgRankRow,MATCH(4,CfgRank,0))),"") | D17: =IF(ISNUMBER(MATCH(4,CfgRank,0)),INDEX('Guided Configurator'!$H:$H,INDEX(CfgRankRow,MATCH(4,CfgRank,0))),"") | E17: =IF(ISNUMBER(MATCH(4,CfgRank,0)),INDEX('Guided Configurator'!$I:$I,INDEX(CfgRankRow,MATCH(4,CfgRank,0))),"") | F17: =IF(ISNUMBER(MATCH(4,CfgRank,0)),INDEX('Guided Configurator'!$M:$M,INDEX(CfgRankRow,MATCH(4,CfgRank,0))),"") | G17: =IF(ISNUMBER(MATCH(4,CfgRank,0)),INDEX('Guided Configurator'!$J:$J,INDEX(CfgRankRow,MATCH(4,CfgRank,0))),"") | H17: =IF(ISNUMBER(MATCH(4,CfgRank,0)),INDEX('Guided Configurator'!$N:$N,INDEX(CfgRankRow,MATCH(4,CfgRank,0))),"")
B18: =IF(ISNUMBER(MATCH(5,CfgRank,0)),INDEX('Guided Configurator'!$O:$O,INDEX(CfgRankRow,MATCH(5,CfgRank,0))),"") | C18: =IF(ISNUMBER(MATCH(5,CfgRank,0)),INDEX('Guided Configurator'!$P:$P,INDEX(CfgRankRow,MATCH(5,CfgRank,0))),"") | D18: =IF(ISNUMBER(MATCH(5,CfgRank,0)),INDEX('Guided Configurator'!$H:$H,INDEX(CfgRankRow,MATCH(5,CfgRank,0))),"") | E18: =IF(ISNUMBER(MATCH(5,CfgRank,0)),INDEX('Guided Configurator'!$I:$I,INDEX(CfgRankRow,MATCH(5,CfgRank,0))),"") | F18: =IF(ISNUMBER(MATCH(5,CfgRank,0)),INDEX('Guided Configurator'!$M:$M,INDEX(CfgRankRow,MATCH(5,CfgRank,0))),"") | G18: =IF(ISNUMBER(MATCH(5,CfgRank,0)),INDEX('Guided Configurator'!$J:$J,INDEX(CfgRankRow,MATCH(5,CfgRank,0))),"") | H18: =IF(ISNUMBER(MATCH(5,CfgRank,0)),INDEX('Guided Configurator'!$N:$N,INDEX(CfgRankRow,MATCH(5,CfgRank,0))),"")
B19: =IF(ISNUMBER(MATCH(6,CfgRank,0)),INDEX('Guided Configurator'!$O:$O,INDEX(CfgRankRow,MATCH(6,CfgRank,0))),"") | C19: =IF(ISNUMBER(MATCH(6,CfgRank,0)),INDEX('Guided Configurator'!$P:$P,INDEX(CfgRankRow,MATCH(6,CfgRank,0))),"") | D19: =IF(ISNUMBER(MATCH(6,CfgRank,0)),INDEX('Guided Configurator'!$H:$H,INDEX(CfgRankRow,MATCH(6,CfgRank,0))),"") | E19: =IF(ISNUMBER(MATCH(6,CfgRank,0)),INDEX('Guided Configurator'!$I:$I,INDEX(CfgRankRow,MATCH(6,CfgRank,0))),"") | F19: =IF(ISNUMBER(MATCH(6,CfgRank,0)),INDEX('Guided Configurator'!$M:$M,INDEX(CfgRankRow,MATCH(6,CfgRank,0))),"") | G19: =IF(ISNUMBER(MATCH(6,CfgRank,0)),INDEX('Guided Configurator'!$J:$J,INDEX(CfgRankRow,MATCH(6,CfgRank,0))),"") | H19: =IF(ISNUMBER(MATCH(6,CfgRank,0)),INDEX('Guided Configurator'!$N:$N,INDEX(CfgRankRow,MATCH(6,CfgRank,0))),"")
B20: =IF(ISNUMBER(MATCH(7,CfgRank,0)),INDEX('Guided Configurator'!$O:$O,INDEX(CfgRankRow,MATCH(7,CfgRank,0))),"") | C20: =IF(ISNUMBER(MATCH(7,CfgRank,0)),INDEX('Guided Configurator'!$P:$P,INDEX(CfgRankRow,MATCH(7,CfgRank,0))),"") | D20: =IF(ISNUMBER(MATCH(7,CfgRank,0)),INDEX('Guided Configurator'!$H:$H,INDEX(CfgRankRow,MATCH(7,CfgRank,0))),"") | E20: =IF(ISNUMBER(MATCH(7,CfgRank,0)),INDEX('Guided Configurator'!$I:$I,INDEX(CfgRankRow,MATCH(7,CfgRank,0))),"") | F20: =IF(ISNUMBER(MATCH(7,CfgRank,0)),INDEX('Guided Configurator'!$M:$M,INDEX(CfgRankRow,MATCH(7,CfgRank,0))),"") | G20: =IF(ISNUMBER(MATCH(7,CfgRank,0)),INDEX('Guided Configurator'!$J:$J,INDEX(CfgRankRow,MATCH(7,CfgRank,0))),"") | H20: =IF(ISNUMBER(MATCH(7,CfgRank,0)),INDEX('Guided Configurator'!$N:$N,INDEX(CfgRankRow,MATCH(7,CfgRank,0))),"")
B21: =IF(ISNUMBER(MATCH(8,CfgRank,0)),INDEX('Guided Configurator'!$O:$O,INDEX(CfgRankRow,MATCH(8,CfgRank,0))),"") | C21: =IF(ISNUMBER(MATCH(8,CfgRank,0)),INDEX('Guided Configurator'!$P:$P,INDEX(CfgRankRow,MATCH(8,CfgRank,0))),"") | D21: =IF(ISNUMBER(MATCH(8,CfgRank,0)),INDEX('Guided Configurator'!$H:$H,INDEX(CfgRankRow,MATCH(8,CfgRank,0))),"") | E21: =IF(ISNUMBER(MATCH(8,CfgRank,0)),INDEX('Guided Configurator'!$I:$I,INDEX(CfgRankRow,MATCH(8,CfgRank,0))),"") | F21: =IF(ISNUMBER(MATCH(8,CfgRank,0)),INDEX('Guided Configurator'!$M:$M,INDEX(CfgRankRow,MATCH(8,CfgRank,0))),"") | G21: =IF(ISNUMBER(MATCH(8,CfgRank,0)),INDEX('Guided Configurator'!$J:$J,INDEX(CfgRankRow,MATCH(8,CfgRank,0))),"") | H21: =IF(ISNUMBER(MATCH(8,CfgRank,0)),INDEX('Guided Configurator'!$N:$N,INDEX(CfgRankRow,MATCH(8,CfgRank,0))),"")
B22: =IF(ISNUMBER(MATCH(9,CfgRank,0)),INDEX('Guided Configurator'!$O:$O,INDEX(CfgRankRow,MATCH(9,CfgRank,0))),"") | C22: =IF(ISNUMBER(MATCH(9,CfgRank,0)),INDEX('Guided Configurator'!$P:$P,INDEX(CfgRankRow,MATCH(9,CfgRank,0))),"") | D22: =IF(ISNUMBER(MATCH(9,CfgRank,0)),INDEX('Guided Configurator'!$H:$H,INDEX(CfgRankRow,MATCH(9,CfgRank,0))),"") | E22: =IF(ISNUMBER(MATCH(9,CfgRank,0)),INDEX('Guided Configurator'!$I:$I,INDEX(CfgRankRow,MATCH(9,CfgRank,0))),"") | F22: =IF(ISNUMBER(MATCH(9,CfgRank,0)),INDEX('Guided Configurator'!$M:$M,INDEX(CfgRankRow,MATCH(9,CfgRank,0))),"") | G22: =IF(ISNUMBER(MATCH(9,CfgRank,0)),INDEX('Guided Configurator'!$J:$J,INDEX(CfgRankRow,MATCH(9,CfgRank,0))),"") | H22: =IF(ISNUMBER(MATCH(9,CfgRank,0)),INDEX('Guided Configurator'!$N:$N,INDEX(CfgRankRow,MATCH(9,CfgRank,0))),"")
B23: =IF(ISNUMBER(MATCH(10,CfgRank,0)),INDEX('Guided Configurator'!$O:$O,INDEX(CfgRankRow,MATCH(10,CfgRank,0))),"") | C23: =IF(ISNUMBER(MATCH(10,CfgRank,0)),INDEX('Guided Configurator'!$P:$P,INDEX(CfgRankRow,MATCH(10,CfgRank,0))),"") | D23: =IF(ISNUMBER(MATCH(10,CfgRank,0)),INDEX('Guided Configurator'!$H:$H,INDEX(CfgRankRow,MATCH(10,CfgRank,0))),"") | E23: =IF(ISNUMBER(MATCH(10,CfgRank,0)),INDEX('Guided Configurator'!$I:$I,INDEX(CfgRankRow,MATCH(10,CfgRank,0))),"") | F23: =IF(ISNUMBER(MATCH(10,CfgRank,0)),INDEX('Guided Configurator'!$M:$M,INDEX(CfgRankRow,MATCH(10,CfgRank,0))),"") | G23: =IF(ISNUMBER(MATCH(10,CfgRank,0)),INDEX('Guided Configurator'!$J:$J,INDEX(CfgRankRow,MATCH(10,CfgRank,0))),"") | H23: =IF(ISNUMBER(MATCH(10,CfgRank,0)),INDEX('Guided Configurator'!$N:$N,INDEX(CfgRankRow,MATCH(10,CfgRank,0))),"")
B25: ACCESSORIES & SERVICES
B26: SKU | C26: Description | D26: Qty | E26: Days | F26: Rate | G26: Disc | H26: Amount
B27: =IF(ISNUMBER(MATCH(1,AccRank,0)),INDEX('Accessories & Services'!$C:$C,INDEX(AccRankRow,MATCH(1,AccRank,0))),"") | C27: =IF(ISNUMBER(MATCH(1,AccRank,0)),INDEX('Accessories & Services'!$D:$D,INDEX(AccRankRow,MATCH(1,AccRank,0))),"") | D27: =IF(ISNUMBER(MATCH(1,AccRank,0)),INDEX('Accessories & Services'!$G:$G,INDEX(AccRankRow,MATCH(1,AccRank,0))),"") | E27: =IF(ISNUMBER(MATCH(1,AccRank,0)),IF(INDEX('Accessories & Services'!$F:$F,INDEX(AccRankRow,MATCH(1,AccRank,0)))="One-Time","One-Time",INDEX('Accessories & Services'!$H:$H,INDEX(AccRankRow,MATCH(1,AccRank,0)))),"") | F27: =IF(ISNUMBER(MATCH(1,AccRank,0)),INDEX('Accessories & Services'!$K:$K,INDEX(AccRankRow,MATCH(1,AccRank,0))),"") | G27: =IF(ISNUMBER(MATCH(1,AccRank,0)),INDEX('Accessories & Services'!$L:$L,INDEX(AccRankRow,MATCH(1,AccRank,0))),"") | H27: =IF(ISNUMBER(MATCH(1,AccRank,0)),INDEX('Accessories & Services'!$M:$M,INDEX(AccRankRow,MATCH(1,AccRank,0))),"")
B28: =IF(ISNUMBER(MATCH(2,AccRank,0)),INDEX('Accessories & Services'!$C:$C,INDEX(AccRankRow,MATCH(2,AccRank,0))),"") | C28: =IF(ISNUMBER(MATCH(2,AccRank,0)),INDEX('Accessories & Services'!$D:$D,INDEX(AccRankRow,MATCH(2,AccRank,0))),"") | D28: =IF(ISNUMBER(MATCH(2,AccRank,0)),INDEX('Accessories & Services'!$G:$G,INDEX(AccRankRow,MATCH(2,AccRank,0))),"") | E28: =IF(ISNUMBER(MATCH(2,AccRank,0)),IF(INDEX('Accessories & Services'!$F:$F,INDEX(AccRankRow,MATCH(2,AccRank,0)))="One-Time","One-Time",INDEX('Accessories & Services'!$H:$H,INDEX(AccRankRow,MATCH(2,AccRank,0)))),"") | F28: =IF(ISNUMBER(MATCH(2,AccRank,0)),INDEX('Accessories & Services'!$K:$K,INDEX(AccRankRow,MATCH(2,AccRank,0))),"") | G28: =IF(ISNUMBER(MATCH(2,AccRank,0)),INDEX('Accessories & Services'!$L:$L,INDEX(AccRankRow,MATCH(2,AccRank,0))),"") | H28: =IF(ISNUMBER(MATCH(2,AccRank,0)),INDEX('Accessories & Services'!$M:$M,INDEX(AccRankRow,MATCH(2,AccRank,0))),"")
B29: =IF(ISNUMBER(MATCH(3,AccRank,0)),INDEX('Accessories & Services'!$C:$C,INDEX(AccRankRow,MATCH(3,AccRank,0))),"") | C29: =IF(ISNUMBER(MATCH(3,AccRank,0)),INDEX('Accessories & Services'!$D:$D,INDEX(AccRankRow,MATCH(3,AccRank,0))),"") | D29: =IF(ISNUMBER(MATCH(3,AccRank,0)),INDEX('Accessories & Services'!$G:$G,INDEX(AccRankRow,MATCH(3,AccRank,0))),"") | E29: =IF(ISNUMBER(MATCH(3,AccRank,0)),IF(INDEX('Accessories & Services'!$F:$F,INDEX(AccRankRow,MATCH(3,AccRank,0)))="One-Time","One-Time",INDEX('Accessories & Services'!$H:$H,INDEX(AccRankRow,MATCH(3,AccRank,0)))),"") | F29: =IF(ISNUMBER(MATCH(3,AccRank,0)),INDEX('Accessories & Services'!$K:$K,INDEX(AccRankRow,MATCH(3,AccRank,0))),"") | G29: =IF(ISNUMBER(MATCH(3,AccRank,0)),INDEX('Accessories & Services'!$L:$L,INDEX(AccRankRow,MATCH(3,AccRank,0))),"") | H29: =IF(ISNUMBER(MATCH(3,AccRank,0)),INDEX('Accessories & Services'!$M:$M,INDEX(AccRankRow,MATCH(3,AccRank,0))),"")
B30: =IF(ISNUMBER(MATCH(4,AccRank,0)),INDEX('Accessories & Services'!$C:$C,INDEX(AccRankRow,MATCH(4,AccRank,0))),"") | C30: =IF(ISNUMBER(MATCH(4,AccRank,0)),INDEX('Accessories & Services'!$D:$D,INDEX(AccRankRow,MATCH(4,AccRank,0))),"") | D30: =IF(ISNUMBER(MATCH(4,AccRank,0)),INDEX('Accessories & Services'!$G:$G,INDEX(AccRankRow,MATCH(4,AccRank,0))),"") | E30: =IF(ISNUMBER(MATCH(4,AccRank,0)),IF(INDEX('Accessories & Services'!$F:$F,INDEX(AccRankRow,MATCH(4,AccRank,0)))="One-Time","One-Time",INDEX('Accessories & Services'!$H:$H,INDEX(AccRankRow,MATCH(4,AccRank,0)))),"") | F30: =IF(ISNUMBER(MATCH(4,AccRank,0)),INDEX('Accessories & Services'!$K:$K,INDEX(AccRankRow,MATCH(4,AccRank,0))),"") | G30: =IF(ISNUMBER(MATCH(4,AccRank,0)),INDEX('Accessories & Services'!$L:$L,INDEX(AccRankRow,MATCH(4,AccRank,0))),"") | H30: =IF(ISNUMBER(MATCH(4,AccRank,0)),INDEX('Accessories & Services'!$M:$M,INDEX(AccRankRow,MATCH(4,AccRank,0))),"")
B31: =IF(ISNUMBER(MATCH(5,AccRank,0)),INDEX('Accessories & Services'!$C:$C,INDEX(AccRankRow,MATCH(5,AccRank,0))),"") | C31: =IF(ISNUMBER(MATCH(5,AccRank,0)),INDEX('Accessories & Services'!$D:$D,INDEX(AccRankRow,MATCH(5,AccRank,0))),"") | D31: =IF(ISNUMBER(MATCH(5,AccRank,0)),INDEX('Accessories & Services'!$G:$G,INDEX(AccRankRow,MATCH(5,AccRank,0))),"") | E31: =IF(ISNUMBER(MATCH(5,AccRank,0)),IF(INDEX('Accessories & Services'!$F:$F,INDEX(AccRankRow,MATCH(5,AccRank,0)))="One-Time","One-Time",INDEX('Accessories & Services'!$H:$H,INDEX(AccRankRow,MATCH(5,AccRank,0)))),"") | F31: =IF(ISNUMBER(MATCH(5,AccRank,0)),INDEX('Accessories & Services'!$K:$K,INDEX(AccRankRow,MATCH(5,AccRank,0))),"") | G31: =IF(ISNUMBER(MATCH(5,AccRank,0)),INDEX('Accessories & Services'!$L:$L,INDEX(AccRankRow,MATCH(5,AccRank,0))),"") | H31: =IF(ISNUMBER(MATCH(5,AccRank,0)),INDEX('Accessories & Services'!$M:$M,INDEX(AccRankRow,MATCH(5,AccRank,0))),"")
B32: =IF(ISNUMBER(MATCH(6,AccRank,0)),INDEX('Accessories & Services'!$C:$C,INDEX(AccRankRow,MATCH(6,AccRank,0))),"") | C32: =IF(ISNUMBER(MATCH(6,AccRank,0)),INDEX('Accessories & Services'!$D:$D,INDEX(AccRankRow,MATCH(6,AccRank,0))),"") | D32: =IF(ISNUMBER(MATCH(6,AccRank,0)),INDEX('Accessories & Services'!$G:$G,INDEX(AccRankRow,MATCH(6,AccRank,0))),"") | E32: =IF(ISNUMBER(MATCH(6,AccRank,0)),IF(INDEX('Accessories & Services'!$F:$F,INDEX(AccRankRow,MATCH(6,AccRank,0)))="One-Time","One-Time",INDEX('Accessories & Services'!$H:$H,INDEX(AccRankRow,MATCH(6,AccRank,0)))),"") | F32: =IF(ISNUMBER(MATCH(6,AccRank,0)),INDEX('Accessories & Services'!$K:$K,INDEX(AccRankRow,MATCH(6,AccRank,0))),"") | G32: =IF(ISNUMBER(MATCH(6,AccRank,0)),INDEX('Accessories & Services'!$L:$L,INDEX(AccRankRow,MATCH(6,AccRank,0))),"") | H32: =IF(ISNUMBER(MATCH(6,AccRank,0)),INDEX('Accessories & Services'!$M:$M,INDEX(AccRankRow,MATCH(6,AccRank,0))),"")
B33: =IF(ISNUMBER(MATCH(7,AccRank,0)),INDEX('Accessories & Services'!$C:$C,INDEX(AccRankRow,MATCH(7,AccRank,0))),"") | C33: =IF(ISNUMBER(MATCH(7,AccRank,0)),INDEX('Accessories & Services'!$D:$D,INDEX(AccRankRow,MATCH(7,AccRank,0))),"") | D33: =IF(ISNUMBER(MATCH(7,AccRank,0)),INDEX('Accessories & Services'!$G:$G,INDEX(AccRankRow,MATCH(7,AccRank,0))),"") | E33: =IF(ISNUMBER(MATCH(7,AccRank,0)),IF(INDEX('Accessories & Services'!$F:$F,INDEX(AccRankRow,MATCH(7,AccRank,0)))="One-Time","One-Time",INDEX('Accessories & Services'!$H:$H,INDEX(AccRankRow,MATCH(7,AccRank,0)))),"") | F33: =IF(ISNUMBER(MATCH(7,AccRank,0)),INDEX('Accessories & Services'!$K:$K,INDEX(AccRankRow,MATCH(7,AccRank,0))),"") | G33: =IF(ISNUMBER(MATCH(7,AccRank,0)),INDEX('Accessories & Services'!$L:$L,INDEX(AccRankRow,MATCH(7,AccRank,0))),"") | H33: =IF(ISNUMBER(MATCH(7,AccRank,0)),INDEX('Accessories & Services'!$M:$M,INDEX(AccRankRow,MATCH(7,AccRank,0))),"")
B34: =IF(ISNUMBER(MATCH(8,AccRank,0)),INDEX('Accessories & Services'!$C:$C,INDEX(AccRankRow,MATCH(8,AccRank,0))),"") | C34: =IF(ISNUMBER(MATCH(8,AccRank,0)),INDEX('Accessories & Services'!$D:$D,INDEX(AccRankRow,MATCH(8,AccRank,0))),"") | D34: =IF(ISNUMBER(MATCH(8,AccRank,0)),INDEX('Accessories & Services'!$G:$G,INDEX(AccRankRow,MATCH(8,AccRank,0))),"") | E34: =IF(ISNUMBER(MATCH(8,AccRank,0)),IF(INDEX('Accessories & Services'!$F:$F,INDEX(AccRankRow,MATCH(8,AccRank,0)))="One-Time","One-Time",INDEX('Accessories & Services'!$H:$H,INDEX(AccRankRow,MATCH(8,AccRank,0)))),"") | F34: =IF(ISNUMBER(MATCH(8,AccRank,0)),INDEX('Accessories & Services'!$K:$K,INDEX(AccRankRow,MATCH(8,AccRank,0))),"") | G34: =IF(ISNUMBER(MATCH(8,AccRank,0)),INDEX('Accessories & Services'!$L:$L,INDEX(AccRankRow,MATCH(8,AccRank,0))),"") | H34: =IF(ISNUMBER(MATCH(8,AccRank,0)),INDEX('Accessories & Services'!$M:$M,INDEX(AccRankRow,MATCH(8,AccRank,0))),"")
B35: =IF(ISNUMBER(MATCH(9,AccRank,0)),INDEX('Accessories & Services'!$C:$C,INDEX(AccRankRow,MATCH(9,AccRank,0))),"") | C35: =IF(ISNUMBER(MATCH(9,AccRank,0)),INDEX('Accessories & Services'!$D:$D,INDEX(AccRankRow,MATCH(9,AccRank,0))),"") | D35: =IF(ISNUMBER(MATCH(9,AccRank,0)),INDEX('Accessories & Services'!$G:$G,INDEX(AccRankRow,MATCH(9,AccRank,0))),"") | E35: =IF(ISNUMBER(MATCH(9,AccRank,0)),IF(INDEX('Accessories & Services'!$F:$F,INDEX(AccRankRow,MATCH(9,AccRank,0)))="One-Time","One-Time",INDEX('Accessories & Services'!$H:$H,INDEX(AccRankRow,MATCH(9,AccRank,0)))),"") | F35: =IF(ISNUMBER(MATCH(9,AccRank,0)),INDEX('Accessories & Services'!$K:$K,INDEX(AccRankRow,MATCH(9,AccRank,0))),"") | G35: =IF(ISNUMBER(MATCH(9,AccRank,0)),INDEX('Accessories & Services'!$L:$L,INDEX(AccRankRow,MATCH(9,AccRank,0))),"") | H35: =IF(ISNUMBER(MATCH(9,AccRank,0)),INDEX('Accessories & Services'!$M:$M,INDEX(AccRankRow,MATCH(9,AccRank,0))),"")
B36: =IF(ISNUMBER(MATCH(10,AccRank,0)),INDEX('Accessories & Services'!$C:$C,INDEX(AccRankRow,MATCH(10,AccRank,0))),"") | C36: =IF(ISNUMBER(MATCH(10,AccRank,0)),INDEX('Accessories & Services'!$D:$D,INDEX(AccRankRow,MATCH(10,AccRank,0))),"") | D36: =IF(ISNUMBER(MATCH(10,AccRank,0)),INDEX('Accessories & Services'!$G:$G,INDEX(AccRankRow,MATCH(10,AccRank,0))),"") | E36: =IF(ISNUMBER(MATCH(10,AccRank,0)),IF(INDEX('Accessories & Services'!$F:$F,INDEX(AccRankRow,MATCH(10,AccRank,0)))="One-Time","One-Time",INDEX('Accessories & Services'!$H:$H,INDEX(AccRankRow,MATCH(10,AccRank,0)))),"") | F36: =IF(ISNUMBER(MATCH(10,AccRank,0)),INDEX('Accessories & Services'!$K:$K,INDEX(AccRankRow,MATCH(10,AccRank,0))),"") | G36: =IF(ISNUMBER(MATCH(10,AccRank,0)),INDEX('Accessories & Services'!$L:$L,INDEX(AccRankRow,MATCH(10,AccRank,0))),"") | H36: =IF(ISNUMBER(MATCH(10,AccRank,0)),INDEX('Accessories & Services'!$M:$M,INDEX(AccRankRow,MATCH(10,AccRank,0))),"")
B37: =IF(ISNUMBER(MATCH(11,AccRank,0)),INDEX('Accessories & Services'!$C:$C,INDEX(AccRankRow,MATCH(11,AccRank,0))),"") | C37: =IF(ISNUMBER(MATCH(11,AccRank,0)),INDEX('Accessories & Services'!$D:$D,INDEX(AccRankRow,MATCH(11,AccRank,0))),"") | D37: =IF(ISNUMBER(MATCH(11,AccRank,0)),INDEX('Accessories & Services'!$G:$G,INDEX(AccRankRow,MATCH(11,AccRank,0))),"") | E37: =IF(ISNUMBER(MATCH(11,AccRank,0)),IF(INDEX('Accessories & Services'!$F:$F,INDEX(AccRankRow,MATCH(11,AccRank,0)))="One-Time","One-Time",INDEX('Accessories & Services'!$H:$H,INDEX(AccRankRow,MATCH(11,AccRank,0)))),"") | F37: =IF(ISNUMBER(MATCH(11,AccRank,0)),INDEX('Accessories & Services'!$K:$K,INDEX(AccRankRow,MATCH(11,AccRank,0))),"") | G37: =IF(ISNUMBER(MATCH(11,AccRank,0)),INDEX('Accessories & Services'!$L:$L,INDEX(AccRankRow,MATCH(11,AccRank,0))),"") | H37: =IF(ISNUMBER(MATCH(11,AccRank,0)),INDEX('Accessories & Services'!$M:$M,INDEX(AccRankRow,MATCH(11,AccRank,0))),"")
B38: =IF(ISNUMBER(MATCH(12,AccRank,0)),INDEX('Accessories & Services'!$C:$C,INDEX(AccRankRow,MATCH(12,AccRank,0))),"") | C38: =IF(ISNUMBER(MATCH(12,AccRank,0)),INDEX('Accessories & Services'!$D:$D,INDEX(AccRankRow,MATCH(12,AccRank,0))),"") | D38: =IF(ISNUMBER(MATCH(12,AccRank,0)),INDEX('Accessories & Services'!$G:$G,INDEX(AccRankRow,MATCH(12,AccRank,0))),"") | E38: =IF(ISNUMBER(MATCH(12,AccRank,0)),IF(INDEX('Accessories & Services'!$F:$F,INDEX(AccRankRow,MATCH(12,AccRank,0)))="One-Time","One-Time",INDEX('Accessories & Services'!$H:$H,INDEX(AccRankRow,MATCH(12,AccRank,0)))),"") | F38: =IF(ISNUMBER(MATCH(12,AccRank,0)),INDEX('Accessories & Services'!$K:$K,INDEX(AccRankRow,MATCH(12,AccRank,0))),"") | G38: =IF(ISNUMBER(MATCH(12,AccRank,0)),INDEX('Accessories & Services'!$L:$L,INDEX(AccRankRow,MATCH(12,AccRank,0))),"") | H38: =IF(ISNUMBER(MATCH(12,AccRank,0)),INDEX('Accessories & Services'!$M:$M,INDEX(AccRankRow,MATCH(12,AccRank,0))),"")
B39: =IF(ISNUMBER(MATCH(13,AccRank,0)),INDEX('Accessories & Services'!$C:$C,INDEX(AccRankRow,MATCH(13,AccRank,0))),"") | C39: =IF(ISNUMBER(MATCH(13,AccRank,0)),INDEX('Accessories & Services'!$D:$D,INDEX(AccRankRow,MATCH(13,AccRank,0))),"") | D39: =IF(ISNUMBER(MATCH(13,AccRank,0)),INDEX('Accessories & Services'!$G:$G,INDEX(AccRankRow,MATCH(13,AccRank,0))),"") | E39: =IF(ISNUMBER(MATCH(13,AccRank,0)),IF(INDEX('Accessories & Services'!$F:$F,INDEX(AccRankRow,MATCH(13,AccRank,0)))="One-Time","One-Time",INDEX('Accessories & Services'!$H:$H,INDEX(AccRankRow,MATCH(13,AccRank,0)))),"") | F39: =IF(ISNUMBER(MATCH(13,AccRank,0)),INDEX('Accessories & Services'!$K:$K,INDEX(AccRankRow,MATCH(13,AccRank,0))),"") | G39: =IF(ISNUMBER(MATCH(13,AccRank,0)),INDEX('Accessories & Services'!$L:$L,INDEX(AccRankRow,MATCH(13,AccRank,0))),"") | H39: =IF(ISNUMBER(MATCH(13,AccRank,0)),INDEX('Accessories & Services'!$M:$M,INDEX(AccRankRow,MATCH(13,AccRank,0))),"")
B40: =IF(ISNUMBER(MATCH(14,AccRank,0)),INDEX('Accessories & Services'!$C:$C,INDEX(AccRankRow,MATCH(14,AccRank,0))),"") | C40: =IF(ISNUMBER(MATCH(14,AccRank,0)),INDEX('Accessories & Services'!$D:$D,INDEX(AccRankRow,MATCH(14,AccRank,0))),"") | D40: =IF(ISNUMBER(MATCH(14,AccRank,0)),INDEX('Accessories & Services'!$G:$G,INDEX(AccRankRow,MATCH(14,AccRank,0))),"") | E40: =IF(ISNUMBER(MATCH(14,AccRank,0)),IF(INDEX('Accessories & Services'!$F:$F,INDEX(AccRankRow,MATCH(14,AccRank,0)))="One-Time","One-Time",INDEX('Accessories & Services'!$H:$H,INDEX(AccRankRow,MATCH(14,AccRank,0)))),"") | F40: =IF(ISNUMBER(MATCH(14,AccRank,0)),INDEX('Accessories & Services'!$K:$K,INDEX(AccRankRow,MATCH(14,AccRank,0))),"") | G40: =IF(ISNUMBER(MATCH(14,AccRank,0)),INDEX('Accessories & Services'!$L:$L,INDEX(AccRankRow,MATCH(14,AccRank,0))),"") | H40: =IF(ISNUMBER(MATCH(14,AccRank,0)),INDEX('Accessories & Services'!$M:$M,INDEX(AccRankRow,MATCH(14,AccRank,0))),"")
B41: =IF(ISNUMBER(MATCH(15,AccRank,0)),INDEX('Accessories & Services'!$C:$C,INDEX(AccRankRow,MATCH(15,AccRank,0))),"") | C41: =IF(ISNUMBER(MATCH(15,AccRank,0)),INDEX('Accessories & Services'!$D:$D,INDEX(AccRankRow,MATCH(15,AccRank,0))),"") | D41: =IF(ISNUMBER(MATCH(15,AccRank,0)),INDEX('Accessories & Services'!$G:$G,INDEX(AccRankRow,MATCH(15,AccRank,0))),"") | E41: =IF(ISNUMBER(MATCH(15,AccRank,0)),IF(INDEX('Accessories & Services'!$F:$F,INDEX(AccRankRow,MATCH(15,AccRank,0)))="One-Time","One-Time",INDEX('Accessories & Services'!$H:$H,INDEX(AccRankRow,MATCH(15,AccRank,0)))),"") | F41: =IF(ISNUMBER(MATCH(15,AccRank,0)),INDEX('Accessories & Services'!$K:$K,INDEX(AccRankRow,MATCH(15,AccRank,0))),"") | G41: =IF(ISNUMBER(MATCH(15,AccRank,0)),INDEX('Accessories & Services'!$L:$L,INDEX(AccRankRow,MATCH(15,AccRank,0))),"") | H41: =IF(ISNUMBER(MATCH(15,AccRank,0)),INDEX('Accessories & Services'!$M:$M,INDEX(AccRankRow,MATCH(15,AccRank,0))),"")
B42: =IF(ISNUMBER(MATCH(16,AccRank,0)),INDEX('Accessories & Services'!$C:$C,INDEX(AccRankRow,MATCH(16,AccRank,0))),"") | C42: =IF(ISNUMBER(MATCH(16,AccRank,0)),INDEX('Accessories & Services'!$D:$D,INDEX(AccRankRow,MATCH(16,AccRank,0))),"") | D42: =IF(ISNUMBER(MATCH(16,AccRank,0)),INDEX('Accessories & Services'!$G:$G,INDEX(AccRankRow,MATCH(16,AccRank,0))),"") | E42: =IF(ISNUMBER(MATCH(16,AccRank,0)),IF(INDEX('Accessories & Services'!$F:$F,INDEX(AccRankRow,MATCH(16,AccRank,0)))="One-Time","One-Time",INDEX('Accessories & Services'!$H:$H,INDEX(AccRankRow,MATCH(16,AccRank,0)))),"") | F42: =IF(ISNUMBER(MATCH(16,AccRank,0)),INDEX('Accessories & Services'!$K:$K,INDEX(AccRankRow,MATCH(16,AccRank,0))),"") | G42: =IF(ISNUMBER(MATCH(16,AccRank,0)),INDEX('Accessories & Services'!$L:$L,INDEX(AccRankRow,MATCH(16,AccRank,0))),"") | H42: =IF(ISNUMBER(MATCH(16,AccRank,0)),INDEX('Accessories & Services'!$M:$M,INDEX(AccRankRow,MATCH(16,AccRank,0))),"")
B43: =IF(ISNUMBER(MATCH(17,AccRank,0)),INDEX('Accessories & Services'!$C:$C,INDEX(AccRankRow,MATCH(17,AccRank,0))),"") | C43: =IF(ISNUMBER(MATCH(17,AccRank,0)),INDEX('Accessories & Services'!$D:$D,INDEX(AccRankRow,MATCH(17,AccRank,0))),"") | D43: =IF(ISNUMBER(MATCH(17,AccRank,0)),INDEX('Accessories & Services'!$G:$G,INDEX(AccRankRow,MATCH(17,AccRank,0))),"") | E43: =IF(ISNUMBER(MATCH(17,AccRank,0)),IF(INDEX('Accessories & Services'!$F:$F,INDEX(AccRankRow,MATCH(17,AccRank,0)))="One-Time","One-Time",INDEX('Accessories & Services'!$H:$H,INDEX(AccRankRow,MATCH(17,AccRank,0)))),"") | F43: =IF(ISNUMBER(MATCH(17,AccRank,0)),INDEX('Accessories & Services'!$K:$K,INDEX(AccRankRow,MATCH(17,AccRank,0))),"") | G43: =IF(ISNUMBER(MATCH(17,AccRank,0)),INDEX('Accessories & Services'!$L:$L,INDEX(AccRankRow,MATCH(17,AccRank,0))),"") | H43: =IF(ISNUMBER(MATCH(17,AccRank,0)),INDEX('Accessories & Services'!$M:$M,INDEX(AccRankRow,MATCH(17,AccRank,0))),"")
B44: =IF(ISNUMBER(MATCH(18,AccRank,0)),INDEX('Accessories & Services'!$C:$C,INDEX(AccRankRow,MATCH(18,AccRank,0))),"") | C44: =IF(ISNUMBER(MATCH(18,AccRank,0)),INDEX('Accessories & Services'!$D:$D,INDEX(AccRankRow,MATCH(18,AccRank,0))),"") | D44: =IF(ISNUMBER(MATCH(18,AccRank,0)),INDEX('Accessories & Services'!$G:$G,INDEX(AccRankRow,MATCH(18,AccRank,0))),"") | E44: =IF(ISNUMBER(MATCH(18,AccRank,0)),IF(INDEX('Accessories & Services'!$F:$F,INDEX(AccRankRow,MATCH(18,AccRank,0)))="One-Time","One-Time",INDEX('Accessories & Services'!$H:$H,INDEX(AccRankRow,MATCH(18,AccRank,0)))),"") | F44: =IF(ISNUMBER(MATCH(18,AccRank,0)),INDEX('Accessories & Services'!$K:$K,INDEX(AccRankRow,MATCH(18,AccRank,0))),"") | G44: =IF(ISNUMBER(MATCH(18,AccRank,0)),INDEX('Accessories & Services'!$L:$L,INDEX(AccRankRow,MATCH(18,AccRank,0))),"") | H44: =IF(ISNUMBER(MATCH(18,AccRank,0)),INDEX('Accessories & Services'!$M:$M,INDEX(AccRankRow,MATCH(18,AccRank,0))),"")
B45: =IF(ISNUMBER(MATCH(19,AccRank,0)),INDEX('Accessories & Services'!$C:$C,INDEX(AccRankRow,MATCH(19,AccRank,0))),"") | C45: =IF(ISNUMBER(MATCH(19,AccRank,0)),INDEX('Accessories & Services'!$D:$D,INDEX(AccRankRow,MATCH(19,AccRank,0))),"") | D45: =IF(ISNUMBER(MATCH(19,AccRank,0)),INDEX('Accessories & Services'!$G:$G,INDEX(AccRankRow,MATCH(19,AccRank,0))),"") | E45: =IF(ISNUMBER(MATCH(19,AccRank,0)),IF(INDEX('Accessories & Services'!$F:$F,INDEX(AccRankRow,MATCH(19,AccRank,0)))="One-Time","One-Time",INDEX('Accessories & Services'!$H:$H,INDEX(AccRankRow,MATCH(19,AccRank,0)))),"") | F45: =IF(ISNUMBER(MATCH(19,AccRank,0)),INDEX('Accessories & Services'!$K:$K,INDEX(AccRankRow,MATCH(19,AccRank,0))),"") | G45: =IF(ISNUMBER(MATCH(19,AccRank,0)),INDEX('Accessories & Services'!$L:$L,INDEX(AccRankRow,MATCH(19,AccRank,0))),"") | H45: =IF(ISNUMBER(MATCH(19,AccRank,0)),INDEX('Accessories & Services'!$M:$M,INDEX(AccRankRow,MATCH(19,AccRank,0))),"")
B46: =IF(ISNUMBER(MATCH(20,AccRank,0)),INDEX('Accessories & Services'!$C:$C,INDEX(AccRankRow,MATCH(20,AccRank,0))),"") | C46: =IF(ISNUMBER(MATCH(20,AccRank,0)),INDEX('Accessories & Services'!$D:$D,INDEX(AccRankRow,MATCH(20,AccRank,0))),"") | D46: =IF(ISNUMBER(MATCH(20,AccRank,0)),INDEX('Accessories & Services'!$G:$G,INDEX(AccRankRow,MATCH(20,AccRank,0))),"") | E46: =IF(ISNUMBER(MATCH(20,AccRank,0)),IF(INDEX('Accessories & Services'!$F:$F,INDEX(AccRankRow,MATCH(20,AccRank,0)))="One-Time","One-Time",INDEX('Accessories & Services'!$H:$H,INDEX(AccRankRow,MATCH(20,AccRank,0)))),"") | F46: =IF(ISNUMBER(MATCH(20,AccRank,0)),INDEX('Accessories & Services'!$K:$K,INDEX(AccRankRow,MATCH(20,AccRank,0))),"") | G46: =IF(ISNUMBER(MATCH(20,AccRank,0)),INDEX('Accessories & Services'!$L:$L,INDEX(AccRankRow,MATCH(20,AccRank,0))),"") | H46: =IF(ISNUMBER(MATCH(20,AccRank,0)),INDEX('Accessories & Services'!$M:$M,INDEX(AccRankRow,MATCH(20,AccRank,0))),"")
E47: Subtotal | H47: =Quote_Subtotal -> 0
E48: Freight | H48: =Freight -> 0
E49: Miscellaneous | H49: =Misc_Charge -> 0
E50: =CONCATENATE("Tax (",TEXT(Tax_Rate,"0.0%"),")") -> Tax (0.0%) | H50: =ROUND(Quote_Subtotal*Tax_Rate,2) -> 0
E51: GRAND TOTAL | H51: =Quote_GrandTotal -> 0
B53: Notes:
B54: =IF(Cust_Notes="","",Cust_Notes)
B58: Configured daily rate = base rental rate + applicable sensor upgrade daily rates (USD List column C). Rates marked "One-Time" are flat charges. Quote valid through the date shown. Taxes, freight and miscellaneous as listed.

Sheet Instructions
B2: HOW TO USE THIS RENTAL QUOTING TOOL
B4: 1 | C4: Start Quote tab — fill the yellow inputs: quote number, dates, salesperson, customer details, rental start/end, tax, freight and miscellaneous. Valid Through and Default Rental Days calculate automatically.
B5: 2 | C5: Guided Configurator tab — the main interface. For each of up to 10 lines: pick a Device — G7/G8c (cellular; fulfilled from fleet stock as G7c or G8c), G7X, or EXO area monitor, each as Diffusion or Pumped — then individually select the LEL sensor, O2, Toxic 1 and Toxic 2. For EXO devices you can also add an 8-gas Expansion Module (adds 3-4 extra gases and its daily rate, and slots its code into the SKU). Set Qty, Days and Discount.
B6: 3 | C6: The tool shows Base Daily, Sensor Upgrades Daily, Configured Unit Daily, Extended Total, a config code, a readable configuration description, and a Status (Complete / Duplicate sensors / Unknown rate / Review).
B7: 4 | C7: Accessories & Services tab — add any accessory, bridge, service, monitoring, consumable, calibration gas or training. Set Include = Yes, pick a SKU, choose Daily or One-Time, set Qty/Days/Discount. Use Rate Override for blank/manual-rate lines.
B8: 5 | C8: Quote Summary tab — internal consolidated view of configured equipment plus add-ons with subtotal, freight, misc, tax and grand total.
B9: 6 | C9: Printable Quote tab — clean customer-facing page listing each configured unit (with sensor description) then add-ons and totals. Print area, margins and repeating headers are preset.
B11: PRICING LOGIC & ASSUMPTIONS
C12: • Configured daily rate = Base rental rate (device) + sensor upgrade daily rates + EXO 8-gas expansion module daily rate (if selected). EXO Pumped = EXO base + pump module, both from the Pricing Database.
C13: • Sensor upgrade tiers (from USD List descriptions): Premium Sensors = $3.20/day; Advanced Sensor (CO2) = $8.00/day; VOC/HF (PID, HF) = $12.00/day.
C14: • Standard sensors (H2S, CO, SO2, O2, LEL-IR, LEL-MPS) and No Sensor add $0/day — the source does not list a separate daily rental surcharge for them.
C15: • The dollar surcharge for each tier is a LOOKUP to the hidden Pricing Database (never hardcoded). Tier assignment is stored on the hidden Sensor Rules sheet.
C16: • Config code follows the rental quote SKU convention: RENT-G7C-Q-DIOV-1D (Q = diffusion cartridge, P = pumped; 4 sensor letters sorted ascending, X = empty slot). EXO: RENT-EXO-{module code or X}-{P or X}-{sensor letters}-1D. G7/G8c lines keep the RENT-G7C SKU root — fleet ships G7c or G8c cellular against it.
C17: • LEL slot offers the two valid combustible types (LEL-IR, LEL-MPS) plus No Sensor. O2 slot offers O2 or No Sensor. Toxic slots use the reference toxic list plus No Sensor.
C18: • Duplicate toxic sensors (Toxic 1 = Toxic 2, both non-blank) are flagged in the Status column. Extended amount = Qty x Days x Unit Daily x (1 - Discount).
C19: • RENTAL-ONE-TIME has no rate in the source; it is retained with a blank rate and requires a manual price via the Rate Override column on Accessories & Services.
C20: • List Price (USD List column E) is never used for any calculation.
B22: LEGEND
B23: In | C23: Yellow cells — you type here.
B24: Ca | C24: Grey cells — calculated automatically, do not edit.

Sheet Pricing Database
A1: PRICING DATABASE
A2: Source: 2026-Rental-Pricing-Workbook (USD List sheet). All Daily Rates from USD List column C (DAILY RATE). List Price (col E) is NOT used. Rates valid for 2026.
A4: Category | B4: Lookup Key | C4: SKU | D4: Description | E4: Daily Rate | F4: Source Row
A5: G7C Portables - Diffusion | B5: RENT-G7C | C5: RENT-G7C | D5: Rental service, G7C, diffusion, daily rate | E5: 8 | F5: 6
A6: G7C Portables - Diffusion | B6: RENT-G7C-P | C6: RENT-G7C-P | D6: Rental service, G7C, pump, daily rate | E6: 14.4 | F6: 7
A7: G7C Lone Worker | B7: RENT-G7C-Z | C7: RENT-G7C-Z | D7: Rental service, G7C, standard Z cart, daily rate | E7: 6.4 | F7: 10
A8: G7C Lone Worker | B8: RENT-G7C-S | C8: RENT-G7C-S | D8: Rental service, G7C, single-gas H2S, daily rate | E8: 8 | F8: 11
A9: G7X Portables | B9: RENT-G7X | C9: RENT-G7X | D9: Rental service, G7X, diffusion, daily rate | E9: 8 | F9: 14
A10: G7X Portables | B10: RENT-G7X-P | C10: RENT-G7X-P | D10: Rental service, G7X, pump, daily rate | E10: 14.4 | F10: 15
A11: G7X Portables - Lone Worker and Single Gas | B11: RENT-G7X-Z | C11: RENT-G7X-Z | D11: Rental service, G7X, standard Z cart, daily rate | E11: 6.4 | F11: 18
A12: G7X Portables - Lone Worker and Single Gas | B12: RENT-G7X-S | C12: RENT-G7X-S | D12: Rental service, G7X, single-gas, daily rate | E12: 8 | F12: 19
A13: G7 Bridge | B13: RENT-BRIDGE | C13: RENT-BRIDGE | D13: Rental service, G7 bridge, daily rate | E13: 12.8 | F13: 22
A14: EXO Area Monitor | B14: RENT-G7EXO | C14: RENT-G7EXO | D14: Rental service, EXO, daily rate | E14: 33.6 | F14: 25
A15: EXO Area Monitor | B15: RENT-G7EXO-PUMP | C15: RENT-G7EXO-PUMP | D15: Rental service, EXO, pump module, daily rate | E15: 12 | F15: 26
A16: EXO Area Monitor | B16: RENT-G7EXO-SAT | C16: RENT-G7EXO-SAT | D16: Rental service, EXO, satellite module, daily rate | E16: 28 | F16: 27
... A73: Additional Services | B73: RENT-TECH-HOUR-OT | C73: RENT-TECH-HOUR-OT | D73: Technician time, hourly, OT (callout) | E73: 97.5 | F73: 96
A74: Additional Services | B74: RENTAL-ONE-TIME | C74: RENTAL-ONE-TIME | D74: One time charge - as needed [MANUAL PRICE REQUIRED] | F74: 97
A75: Additional Services | B75: SER-RENTAL | C75: SER-RENTAL | D75: Distributor owned device move fee - up to 50 units | E75: 80 | F75: 98
A76: Additional Services | B76: SER-RENTAL (2) | C76: SER-RENTAL | D76: Distributor owned device move fee - surcharge for units over 50 | E76: 75 | F76: 99
A77: Additional Services | B77: SER-RENTAL (3) | C77: SER-RENTAL | D77: Distributor owned device move fee - per-unit charge over 51 | E77: 1.5 | F77: 100
A78: Additional Services | B78: RENT-TRAIN | C78: RENT-TRAIN | D78: Training, Daily, at Blackline Facility | E78: 1000 | F78: 101
A79: Additional Services | B79: RENT-TRAVEL-1D | C79: RENT-TRAVEL-1D | D79: Training, 1 day, at customer facility | E79: 2800 | F79: 102
A80: Additional Services | B80: RENT-TRAVEL-2D | C80: RENT-TRAVEL-2D | D80: Training, 2 days, at customer facility | E80: 3600 | F80: 103
A81: Additional Services | B81: RENT-TRAVEL-3D | C81: RENT-TRAVEL-3D | D81: Training, 3 days, at customer facility | E81: 4400 | F81: 104
A82: Additional Services | B82: RENT-TRAVEL-4D | C82: RENT-TRAVEL-4D | D82: Training, 4 days, at customer facility | E82: 4800 | F82: 105
A83: Additional Services | B83: RENT-TRAVEL-5D | C83: RENT-TRAVEL-5D | D83: Training, 5 days, at customer facility | E83: 5200 | F83: 106
A84: Additional Services | B84: RENT-AUTOBUMP | C84: RENT-AUTOBUMP | D84: Rental Service, Auto bump & calibration, daily rate | E84: 2.4 | F84: 107
A85: Additional Services | B85: RENT-ALERTLINK | C85: RENT-ALERTLINK | D85: Rental Service, AlertLink, daily rate | E85: 0.8 | F85: 108
A86: Additional Services | B86: RENT-BV | C86: RENT-BV | D86: Rental Service, Blackline 24/7 live monitoring, daily rate | E86: 4 | F86: 109
... A118: Consumables | B118: RENT-GAS-10AL-ZEROAIR | C118: RENT-GAS-10AL-ZEROAIR | D118: Gas, 10AL Gas Cylinder, UN1002 Air, 103L | E118: 233.6 | F118: 143
A119: EXO Area Monitor | B119: RENT-G7EXO-PUMPED | C119: RENT-G7EXO + RENT-G7EXO-PUMP | D119: Rental service, EXO with pump module, daily rate (base + pump) | E119: =E14+E15 | F119: 25+26

Sheet Sensor Rules
A1: SENSOR RULES & TIER MAPPING
A2: Sensor names/codes reproduced from USD-Price-List selector logic (G7 Multi-Gas Purchase). Tier assignment derived from USD List descriptions: Premium Sensors row, Advanced Sensor (CO2) row, VOC/HF (PID,HF) row. Standard sensors add $0. Dollar surcharge is a LOOKUP to Pricing Database, never hardcoded.
A4: TIER | B4: Pricing DB Lookup Key | D4: Sensor Name | E4: Code | F4: Tier | H4: LEL Slot | I4: O2 Slot | J4: Toxic1 Slot | K4: Toxic2 Slot
A5: Standard | D5: LEL-IR | E5: I | F5: Standard | H5: LEL-IR | I5: O2 | J5: HF | K5: HF
A6: Premium | B6: Premium Sensors - Daily | D6: LEL-MPS | E6: F | F6: Standard | H6: LEL-MPS | I6: No Sensor | J6: NH3 | K6: NH3
A7: Advanced | B7: Advanced Sensor - Daily | D7: No Sensor | E7: X | F7: Standard | H7: No Sensor | J7: High-range NH3 | K7: High-range NH3
A8: VOC/HF | B8: VOC/HF Sensor - Daily | D8: O2 | E8: O | F8: Standard | J8: CO2 | K8: COSH
D9: HF | E9: 2 | F9: VOC/HF | J9: O3 | K9: O3
D10: NH3 | E10: A | F10: Premium | J10: H2S | K10: H2S
D11: High-range NH3 | E11: B | F11: Premium | J11: High-range H2S | K11: High-range H2S
D12: CO2 | E12: C | F12: Advanced | J12: NO2 | K12: NO2
D13: O3 | E13: E | F13: Premium | J13: Cl2 | K13: Cl2
D14: H2S | E14: H | F14: Standard | J14: CO | K14: CO
D15: High-range H2S | E15: J | F15: Premium | J15: HCN | K15: HCN
D16: NO2 | E16: K | F16: Premium | J16: CO-H | K16: CO-H
D17: Cl2 | E17: L | F17: Premium | J17: SO2 | K17: SO2
D18: CO | E18: M | F18: Standard | J18: High-range CO | K18: High-range CO
D19: HCN | E19: N | F19: Premium | J19: PID | K19: ClO2
D20: CO-H | E20: R | F20: Premium | J20: ClO2 | K20: No Sensor
D21: SO2 | E21: S | F21: Standard | J21: No Sensor
D22: High-range CO | E22: T | F22: Premium
D23: PID | E23: V | F23: VOC/HF
D24: ClO2 | E24: W | F24: Premium
D25: COSH | E25: D | F25: Premium

Sheet Lists
A1: Device | B1: BaseKey | C1: SKU Prefix | D1: YesNo | F1: Method | H1: CfgRow | I1: Incl | J1: Rank | L1: AccRow | M1: Incl | N1: Rank | P1: EXO 8-Gas Module | Q1: Code | R1: DB Key
A2: G7/G8c Diffusion | B2: RENT-G7C | C2: RENT-G7C-Q | D2: Yes | F2: Daily | H2: 8 | I2: =IF(AND('Guided Configurator'!$C8<>"",'Guided Configurator'!$N8>0),1,0) -> 0 | J2: =IF(I2=1,SUM($I$2:I2),"") | L2: 6 | M2: =IF(AND('Accessories & Services'!$B6="Yes",'Accessories & Services'!$C6<>""),1,0) -> 0 | N2: =IF(M2=1,SUM($M$2:M2),"") | P2: No Module | Q2: X
A3: G7/G8c Pumped | B3: RENT-G7C-P | C3: RENT-G7C-P | D3: No | F3: One-Time | H3: 9 | I3: =IF(AND('Guided Configurator'!$C9<>"",'Guided Configurator'!$N9>0),1,0) -> 0 | J3: =IF(I3=1,SUM($I$2:I3),"") | L3: 7 | M3: =IF(AND('Accessories & Services'!$B7="Yes",'Accessories & Services'!$C7<>""),1,0) -> 0 | N3: =IF(M3=1,SUM($M$2:M3),"") | P3: SO2, PID (SVXX) | Q3: SVXX | R3: RENT-EX8-GEM-01
A4: G7X Diffusion | B4: RENT-G7X | C4: RENT-G7X-Q | H4: 10 | I4: =IF(AND('Guided Configurator'!$C10<>"",'Guided Configurator'!$N10>0),1,0) -> 0 | J4: =IF(I4=1,SUM($I$2:I4),"") | L4: 8 | M4: =IF(AND('Accessories & Services'!$B8="Yes",'Accessories & Services'!$C8<>""),1,0) -> 0 | N4: =IF(M4=1,SUM($M$2:M4),"") | P4: HF, NH3, SO2, PID (2ASV) | Q4: 2ASV | R4: RENT-EX8-GEM-02
A5: G7X Pump | B5: RENT-G7X-P | C5: RENT-G7X-P | H5: 11 | I5: =IF(AND('Guided Configurator'!$C11<>"",'Guided Configurator'!$N11>0),1,0) -> 0 | J5: =IF(I5=1,SUM($I$2:I5),"") | L5: 9 | M5: =IF(AND('Accessories & Services'!$B9="Yes",'Accessories & Services'!$C9<>""),1,0) -> 0 | N5: =IF(M5=1,SUM($M$2:M5),"") | P5: H2, NH3, SO2, PID (6ASV) | Q5: 6ASV | R5: RENT-EX8-GEM-03
A6: EXO Diffusion | B6: RENT-G7EXO | C6: RENT-EXO-~-X | H6: 12 | I6: =IF(AND('Guided Configurator'!$C12<>"",'Guided Configurator'!$N12>0),1,0) -> 0 | J6: =IF(I6=1,SUM($I$2:I6),"") | L6: 10 | M6: =IF(AND('Accessories & Services'!$B10="Yes",'Accessories & Services'!$C10<>""),1,0) -> 0 | N6: =IF(M6=1,SUM($M$2:M6),"") | P6: NH3, H2S, SO2 (AHSX) | Q6: AHSX | R6: RENT-EX8-GEM-04
A7: EXO Pumped | B7: RENT-G7EXO-PUMPED | C7: RENT-EXO-~-P | H7: 13 | I7: =IF(AND('Guided Configurator'!$C13<>"",'Guided Configurator'!$N13>0),1,0) -> 0 | J7: =IF(I7=1,SUM($I$2:I7),"") | L7: 11 | M7: =IF(AND('Accessories & Services'!$B11="Yes",'Accessories & Services'!$C11<>""),1,0) -> 0 | N7: =IF(M7=1,SUM($M$2:M7),"") | P7: H2, NH3, Cl2, PID (6ALV) | Q7: 6ALV | R7: RENT-EX8-GEM-11
H8: 14 | I8: =IF(AND('Guided Configurator'!$C14<>"",'Guided Configurator'!$N14>0),1,0) -> 0 | J8: =IF(I8=1,SUM($I$2:I8),"") | L8: 12 | M8: =IF(AND('Accessories & Services'!$B12="Yes",'Accessories & Services'!$C12<>""),1,0) -> 0 | N8: =IF(M8=1,SUM($M$2:M8),"") | P8: H2, Cl2, HCN, PID (6LNV) | Q8: 6LNV | R8: RENT-EX8-GEM-05
H9: 15 | I9: =IF(AND('Guided Configurator'!$C15<>"",'Guided Configurator'!$N15>0),1,0) -> 0 | J9: =IF(I9=1,SUM($I$2:I9),"") | L9: 13 | M9: =IF(AND('Accessories & Services'!$B13="Yes",'Accessories & Services'!$C13<>""),1,0) -> 0 | N9: =IF(M9=1,SUM($M$2:M9),"") | P9: NH3, Cl2, HCN, PID (ALNV) | Q9: ALNV | R9: RENT-EX8-GEM-06
H10: 16 | I10: =IF(AND('Guided Configurator'!$C16<>"",'Guided Configurator'!$N16>0),1,0) -> 0 | J10: =IF(I10=1,SUM($I$2:I10),"") | L10: 14 | M10: =IF(AND('Accessories & Services'!$B14="Yes",'Accessories & Services'!$C14<>""),1,0) -> 0 | N10: =IF(M10=1,SUM($M$2:M10),"") | P10: HF, H2, HCN (26NX) | Q10: 26NX | R10: RENT-EX8-GEM-07
H11: 17 | I11: =IF(AND('Guided Configurator'!$C17<>"",'Guided Configurator'!$N17>0),1,0) -> 0 | J11: =IF(I11=1,SUM($I$2:I11),"") | L11: 15 | M11: =IF(AND('Accessories & Services'!$B15="Yes",'Accessories & Services'!$C15<>""),1,0) -> 0 | N11: =IF(M11=1,SUM($M$2:M11),"") | P11: HF, NH3, Cl2, PID (2ALV) | Q11: 2ALV | R11: RENT-EX8-GEM-12
L12: 16 | M12: =IF(AND('Accessories & Services'!$B16="Yes",'Accessories & Services'!$C16<>""),1,0) -> 0 | N12: =IF(M12=1,SUM($M$2:M12),"") | P12: NH3, H2S, Cl2, PID (AHLV) | Q12: AHLV | R12: RENT-EX8-GEM-09
L13: 17 | M13: =IF(AND('Accessories & Services'!$B17="Yes",'Accessories & Services'!$C17<>""),1,0) -> 0 | N13: =IF(M13=1,SUM($M$2:M13),"") | P13: O3, H2, Cl2, SO2 (EHLS) | Q13: EHLS | R13: RENT-EX8-GEM-08
L14: 18 | M14: =IF(AND('Accessories & Services'!$B18="Yes",'Accessories & Services'!$C18<>""),1,0) -> 0 | N14: =IF(M14=1,SUM($M$2:M14),"")
L15: 19 | M15: =IF(AND('Accessories & Services'!$B19="Yes",'Accessories & Services'!$C19<>""),1,0) -> 0 | N15: =IF(M15=1,SUM($M$2:M15),"")
L16: 20 | M16: =IF(AND('Accessories & Services'!$B20="Yes",'Accessories & Services'!$C20<>""),1,0) -> 0 | N16: =IF(M16=1,SUM($M$2:M16),"")
L17: 21 | M17: =IF(AND('Accessories & Services'!$B21="Yes",'Accessories & Services'!$C21<>""),1,0) -> 0 | N17: =IF(M17=1,SUM($M$2:M17),"")
L18: 22 | M18: =IF(AND('Accessories & Services'!$B22="Yes",'Accessories & Services'!$C22<>""),1,0) -> 0 | N18: =IF(M18=1,SUM($M$2:M18),"")
L19: 23 | M19: =IF(AND('Accessories & Services'!$B23="Yes",'Accessories & Services'!$C23<>""),1,0) -> 0 | N19: =IF(M19=1,SUM($M$2:M19),"")
L20: 24 | M20: =IF(AND('Accessories & Services'!$B24="Yes",'Accessories & Services'!$C24<>""),1,0) -> 0 | N20: =IF(M20=1,SUM($M$2:M20),"")
L21: 25 | M21: =IF(AND('Accessories & Services'!$B25="Yes",'Accessories & Services'!$C25<>""),1,0) -> 0 | N21: =IF(M21=1,SUM($M$2:M21),"")
L22: 26 | M22: =IF(AND('Accessories & Services'!$B26="Yes",'Accessories & Services'!$C26<>""),1,0) -> 0 | N22: =IF(M22=1,SUM($M$2:M22),"")
L23: 27 | M23: =IF(AND('Accessories & Services'!$B27="Yes",'Accessories & Services'!$C27<>""),1,0) -> 0 | N23: =IF(M23=1,SUM($M$2:M23),"")
L24: 28 | M24: =IF(AND('Accessories & Services'!$B28="Yes",'Accessories & Services'!$C28<>""),1,0) -> 0 | N24: =IF(M24=1,SUM($M$2:M24),"")
L25: 29 | M25: =IF(AND('Accessories & Services'!$B29="Yes",'Accessories & Services'!$C29<>""),1,0) -> 0 | N25: =IF(M25=1,SUM($M$2:M25),"")
... L29: 33 | M29: =IF(AND('Accessories & Services'!$B33="Yes",'Accessories & Services'!$C33<>""),1,0) -> 0 | N29: =IF(M29=1,SUM($M$2:M29),"")
