Workbook

Sheet Quote
A1: RENTAL QUOTE — Blackline Safety
A2: Prepared for (Customer):
A3: Quote Date:
A4: Prepared by:
A5: Rates valid for: | C5: 2026
A6: Discount off list: | C6: 0.2 | D6: (pick 0, 0.10, 0.15, 0.20, 0.25 — applies to discountable items)
A8: # | B8: SKU (pick from list) | C8: Description | D8: List/day | E8: Qty | F8: Days | G8: Unit rate/day | H8: Line Total
A9: 1 | C9: =IF($B9="","",IFERROR(VLOOKUP($B9,'Price List'!$A:$E,2,FALSE),"?")) | D9: =IF($B9="","",IFERROR(VLOOKUP($B9,'Price List'!$A:$E,4,FALSE),"")) | G9: =IF($B9="","",$D9*(1-IF(VLOOKUP($B9,'Price List'!$A:$E,5,FALSE)=1,$C$6,0))) | H9: =IF(OR($B9="",$E9="",$F9=""),0,$G9*$E9*$F9)
A10: 2 | C10: =IF($B10="","",IFERROR(VLOOKUP($B10,'Price List'!$A:$E,2,FALSE),"?")) | D10: =IF($B10="","",IFERROR(VLOOKUP($B10,'Price List'!$A:$E,4,FALSE),"")) | G10: =IF($B10="","",$D10*(1-IF(VLOOKUP($B10,'Price List'!$A:$E,5,FALSE)=1,$C$6,0))) | H10: =IF(OR($B10="",$E10="",$F10=""),0,$G10*$E10*$F10)
A11: 3 | C11: =IF($B11="","",IFERROR(VLOOKUP($B11,'Price List'!$A:$E,2,FALSE),"?")) | D11: =IF($B11="","",IFERROR(VLOOKUP($B11,'Price List'!$A:$E,4,FALSE),"")) | G11: =IF($B11="","",$D11*(1-IF(VLOOKUP($B11,'Price List'!$A:$E,5,FALSE)=1,$C$6,0))) | H11: =IF(OR($B11="",$E11="",$F11=""),0,$G11*$E11*$F11)
A12: 4 | C12: =IF($B12="","",IFERROR(VLOOKUP($B12,'Price List'!$A:$E,2,FALSE),"?")) | D12: =IF($B12="","",IFERROR(VLOOKUP($B12,'Price List'!$A:$E,4,FALSE),"")) | G12: =IF($B12="","",$D12*(1-IF(VLOOKUP($B12,'Price List'!$A:$E,5,FALSE)=1,$C$6,0))) | H12: =IF(OR($B12="",$E12="",$F12=""),0,$G12*$E12*$F12)
A13: 5 | C13: =IF($B13="","",IFERROR(VLOOKUP($B13,'Price List'!$A:$E,2,FALSE),"?")) | D13: =IF($B13="","",IFERROR(VLOOKUP($B13,'Price List'!$A:$E,4,FALSE),"")) | G13: =IF($B13="","",$D13*(1-IF(VLOOKUP($B13,'Price List'!$A:$E,5,FALSE)=1,$C$6,0))) | H13: =IF(OR($B13="",$E13="",$F13=""),0,$G13*$E13*$F13)
A14: 6 | C14: =IF($B14="","",IFERROR(VLOOKUP($B14,'Price List'!$A:$E,2,FALSE),"?")) | D14: =IF($B14="","",IFERROR(VLOOKUP($B14,'Price List'!$A:$E,4,FALSE),"")) | G14: =IF($B14="","",$D14*(1-IF(VLOOKUP($B14,'Price List'!$A:$E,5,FALSE)=1,$C$6,0))) | H14: =IF(OR($B14="",$E14="",$F14=""),0,$G14*$E14*$F14)
A15: 7 | C15: =IF($B15="","",IFERROR(VLOOKUP($B15,'Price List'!$A:$E,2,FALSE),"?")) | D15: =IF($B15="","",IFERROR(VLOOKUP($B15,'Price List'!$A:$E,4,FALSE),"")) | G15: =IF($B15="","",$D15*(1-IF(VLOOKUP($B15,'Price List'!$A:$E,5,FALSE)=1,$C$6,0))) | H15: =IF(OR($B15="",$E15="",$F15=""),0,$G15*$E15*$F15)
A16: 8 | C16: =IF($B16="","",IFERROR(VLOOKUP($B16,'Price List'!$A:$E,2,FALSE),"?")) | D16: =IF($B16="","",IFERROR(VLOOKUP($B16,'Price List'!$A:$E,4,FALSE),"")) | G16: =IF($B16="","",$D16*(1-IF(VLOOKUP($B16,'Price List'!$A:$E,5,FALSE)=1,$C$6,0))) | H16: =IF(OR($B16="",$E16="",$F16=""),0,$G16*$E16*$F16)
A17: 9 | C17: =IF($B17="","",IFERROR(VLOOKUP($B17,'Price List'!$A:$E,2,FALSE),"?")) | D17: =IF($B17="","",IFERROR(VLOOKUP($B17,'Price List'!$A:$E,4,FALSE),"")) | G17: =IF($B17="","",$D17*(1-IF(VLOOKUP($B17,'Price List'!$A:$E,5,FALSE)=1,$C$6,0))) | H17: =IF(OR($B17="",$E17="",$F17=""),0,$G17*$E17*$F17)
A18: 10 | C18: =IF($B18="","",IFERROR(VLOOKUP($B18,'Price List'!$A:$E,2,FALSE),"?")) | D18: =IF($B18="","",IFERROR(VLOOKUP($B18,'Price List'!$A:$E,4,FALSE),"")) | G18: =IF($B18="","",$D18*(1-IF(VLOOKUP($B18,'Price List'!$A:$E,5,FALSE)=1,$C$6,0))) | H18: =IF(OR($B18="",$E18="",$F18=""),0,$G18*$E18*$F18)
A19: 11 | C19: =IF($B19="","",IFERROR(VLOOKUP($B19,'Price List'!$A:$E,2,FALSE),"?")) | D19: =IF($B19="","",IFERROR(VLOOKUP($B19,'Price List'!$A:$E,4,FALSE),"")) | G19: =IF($B19="","",$D19*(1-IF(VLOOKUP($B19,'Price List'!$A:$E,5,FALSE)=1,$C$6,0))) | H19: =IF(OR($B19="",$E19="",$F19=""),0,$G19*$E19*$F19)
A20: 12 | C20: =IF($B20="","",IFERROR(VLOOKUP($B20,'Price List'!$A:$E,2,FALSE),"?")) | D20: =IF($B20="","",IFERROR(VLOOKUP($B20,'Price List'!$A:$E,4,FALSE),"")) | G20: =IF($B20="","",$D20*(1-IF(VLOOKUP($B20,'Price List'!$A:$E,5,FALSE)=1,$C$6,0))) | H20: =IF(OR($B20="",$E20="",$F20=""),0,$G20*$E20*$F20)
... A38: 30 | C38: =IF($B38="","",IFERROR(VLOOKUP($B38,'Price List'!$A:$E,2,FALSE),"?")) | D38: =IF($B38="","",IFERROR(VLOOKUP($B38,'Price List'!$A:$E,4,FALSE),"")) | G38: =IF($B38="","",$D38*(1-IF(VLOOKUP($B38,'Price List'!$A:$E,5,FALSE)=1,$C$6,0))) | H38: =IF(OR($B38="",$E38="",$F38=""),0,$G38*$E38*$F38)
G39: Subtotal | H39: =SUM(H9:H38)
G40: Tax % | H40: 0
G41: Tax | H41: =H39*H40
G42: GRAND TOTAL | H42: =H39+H41
A44: Notes: one-time fees (move fee, training, tech hours, call-out surcharge) are entered as lines with Days = 1. Flat fees ignore the discount.

Sheet Price List
A1: SKU | B1: Description | C1: Category | D1: List Price (daily) | E1: Discountable
A2: RENT-G7C | B2: Rental service, G7C, diffusion, daily rate | C2: G7C Portables - Diffusion | D2: 10 | E2: 1
A3: RENT-G7C-P | B3: Rental service, G7C, pump, daily rate | C3: G7C Portables - Diffusion | D3: 18 | E3: 1
A4: RENT-G7C-Z | B4: Rental service, G7C, standard Z cart, daily rate | C4: G7C Lone Worker | D4: 8 | E4: 1
A5: RENT-G7C-S | B5: Rental service, G7C, single-gas H2S, daily rate | C5: G7C Lone Worker | D5: 10 | E5: 1
A6: RENT-G7X | B6: Rental service, G7X, diffusion, daily rate | C6: G7X Portables | D6: 10 | E6: 1
A7: RENT-G7X-P | B7: Rental service, G7X, pump, daily rate | C7: G7X Portables | D7: 18 | E7: 1
A8: RENT-G7X-Z | B8: Rental service, G7X, standard Z cart, daily rate | C8: G7X Portables - Lone Worker and Single Gas | D8: 8 | E8: 1
A9: RENT-G7X-S | B9: Rental service, G7X, single-gas, daily rate | C9: G7X Portables - Lone Worker and Single Gas | D9: 10 | E9: 1
A10: RENT-BRIDGE | B10: Rental service, G7 bridge, daily rate | C10: G7 Bridge | D10: 16 | E10: 1
A11: RENT-G7EXO | B11: Rental service, EXO, daily rate | C11: EXO Area Monitor | D11: 42 | E11: 1
A12: RENT-G7EXO-PUMP | B12: Rental service, EXO, pump module, daily rate | C12: EXO Area Monitor | D12: 15 | E12: 1
A13: RENT-G7EXO-SAT | B13: Rental service, EXO, satellite module, daily rate | C13: EXO Area Monitor | D13: 35 | E13: 1
... A115: RENT-GAS-10AL-ZEROAIR | B115: Gas, 10AL Gas Cylinder, UN1002 Air, 103L | C115: Consumables | D115: 292 | E115: 1
